{
  "Id": 966782885742161920,
  "QuestionData": {
    "Number": 0,
    "Question": "Which football club has a stand displaying an extract from the nineteenth book of the Old Testament?",
    "QuestionForQuery": "which football club has a stand displaying an extract from the nineteenth book of the old testament?",
    "SearchResult": {
      "jsonResult": "{\"_type\": \"SearchResponse\", \"queryContext\": {\"originalQuery\": \"which football club has a stand displaying an extract from the nineteenth book of the old testament?\"}, \"webPages\": {\"webSearchUrl\": \"https:\\/\\/www.bing.com\\/search?q=which+football+club+has+a+stand+displaying+an+extract+from+the+nineteenth+book+of+the+old+testament%3f\", \"totalEstimatedMatches\": 11300, \"value\": [{\"id\": \"https:\\/\\/api.cognitive.microsoft.com\\/api\\/v7\\/#WebPages.0\", \"name\": \"Game thread - 22nd February 2018, 9pm GMT : HQEurope\", \"url\": \"https:\\/\\/www.reddit.com\\/r\\/HQEurope\\/comments\\/7zhwbk\\/game_thread_22nd_february_2018_9pm_gmt\\/\", \"isFamilyFriendly\": true, \"displayUrl\": \"https:\\/\\/www.reddit.com\\/r\\/HQEurope\\/comments\\/7zhwbk\\/game_thread_22nd...\", \"snippet\": \"Playing somewhere interesting? Took a piece of the $750 pie? Caught out by a Savage Question? Discuss anything to do with tonight's game...\", \"dateLastCrawled\": \"2018-03-20T20:29:00.0000000Z\", \"language\": \"en\"}, {\"id\": \"https:\\/\\/api.cognitive.microsoft.com\\/api\\/v7\\/#WebPages.1\", \"name\": \"index.cfm?RST=UNF&TAD=436538&dl=am - FriendlyDuck\", \"url\": \"http:\\/\\/www.friendlyduck.com\\/AF_TA\\/rel\\/index.cfm?RST=UNF&TAD=436538&dl=am\", \"isFamilyFriendly\": true, \"displayUrl\": \"www.friendlyduck.com\\/AF_TA\\/rel\\/index.cfm?RST=UNF&TAD=436538&dl=am\", \"snippet\": \"We would like to show you a description here but the site won’t allow us.\", \"dateLastCrawled\": \"2018-03-29T12:38:00.0000000Z\", \"language\": \"en\"}, {\"id\": \"https:\\/\\/api.cognitive.microsoft.com\\/api\\/v7\\/#WebPages.2\", \"name\": \"Alibris - Official Site\", \"url\": \"https:\\/\\/www.alibris.com\\/\", \"about\": [{\"name\": \"Alibris\"}, {\"name\": \"Alibris\"}, {\"name\": \"Alibris\"}], \"isFamilyFriendly\": true, \"displayUrl\": \"https:\\/\\/www.alibris.com\", \"snippet\": \"As one of the premier rare book sites on the Internet, Alibris has ... Find the items displaying the ... and Old Classics. Bargain hunters rejoice! Alibris has ...\", \"dateLastCrawled\": \"2018-04-04T13:55:00.0000000Z\", \"language\": \"en\"}, {\"id\": \"https:\\/\\/api.cognitive.microsoft.com\\/api\\/v7\\/#WebPages.3\", \"name\": \"Battle Hymn of the Republic - Wikipedia\", \"url\": \"https:\\/\\/en.wikipedia.org\\/wiki\\/Battle_Hymn_of_the_Republic\", \"about\": [{\"name\": \"Battle Hymn of the Republic\"}, {\"name\": \"Battle Hymn of the Republic\"}], \"isFamilyFriendly\": true, \"displayUrl\": \"https:\\/\\/en.wikipedia.org\\/wiki\\/Battle_Hymn_of_the_Republic\", \"snippet\": \"... (Old Testament, Isaiah 63; ... \\\"The Battle Hymn of the Republic\\\" has been used frequently as an ... and was since made as the club's official chant at Old ...\", \"dateLastCrawled\": \"2018-04-05T07:25:00.0000000Z\", \"language\": \"en\"}, {\"id\": \"https:\\/\\/api.cognitive.microsoft.com\\/api\\/v7\\/#WebPages.4\", \"name\": \"Lincoln College, Oxford - Wikipedia\", \"url\": \"https:\\/\\/en.wikipedia.org\\/wiki\\/Lincoln_College_Oxford\", \"about\": [{\"name\": \"Lincoln College, Oxford\"}, {\"name\": \"Lincoln College, Oxford\"}, {}], \"isFamilyFriendly\": true, \"displayUrl\": \"https:\\/\\/en.wikipedia.org\\/wiki\\/Lincoln_College_Oxford\", \"snippet\": \"Since the nineteenth century, the beer has been flavoured with ivy so ... scenes from the Old Testament ... has media related to Lincoln College, Oxford.\", \"dateLastCrawled\": \"2018-03-16T19:10:00.0000000Z\", \"language\": \"en\"}, {\"id\": \"https:\\/\\/api.cognitive.microsoft.com\\/api\\/v7\\/#WebPages.5\", \"name\": \"Baker Hermeneutics and Interpretation Collection (17 vols ...\", \"url\": \"https:\\/\\/www.logos.com\\/product\\/53528\\/baker-hermeneutics-and-interpretation-collection\", \"isFamilyFriendly\": true, \"displayUrl\": \"https:\\/\\/www.logos.com\\/product\\/53528\\/baker-hermeneutics-and...\", \"snippet\": \"—Journal for the Study of the Old Testament. Tate has provided a helpful ... and the Evangelical Book Club. He has edited ... extract much more meaning out ...\", \"dateLastCrawled\": \"2018-03-31T10:14:00.0000000Z\", \"language\": \"en\"}, {\"id\": \"https:\\/\\/api.cognitive.microsoft.com\\/api\\/v7\\/#WebPages.6\", \"name\": \"English300 Flashcards | Quizlet\", \"url\": \"https:\\/\\/quizlet.com\\/1561632\\/english300-flash-cards\\/\", \"isFamilyFriendly\": true, \"displayUrl\": \"https:\\/\\/quizlet.com\\/1561632\\/english300-flash-cards\", \"snippet\": \"Start studying English300. Learn ... the team had put on a marvelous display out in Georgia. • in a public ... 4 a short extract from a book or other ...\", \"dateLastCrawled\": \"2018-03-21T07:26:00.0000000Z\", \"language\": \"en\"}, {\"id\": \"https:\\/\\/api.cognitive.microsoft.com\\/api\\/v7\\/#WebPages.7\", \"name\": \"MWP: William Faulkner (1897-1962) - University of Mississippi\", \"url\": \"http:\\/\\/www.olemiss.edu\\/mwp\\/dir\\/faulkner_william\\/\", \"about\": [{\"name\": \"William Faulkner\"}], \"isFamilyFriendly\": true, \"displayUrl\": \"www.olemiss.edu\\/mwp\\/dir\\/faulkner_william\", \"snippet\": \"Information about writer William Faulkner, ... lament over his dead son in the Old Testament, ... to take a public stand as a ...\", \"dateLastCrawled\": \"2018-04-05T11:41:00.0000000Z\", \"language\": \"en\"}, {\"id\": \"https:\\/\\/api.cognitive.microsoft.com\\/api\\/v7\\/#WebPages.8\", \"name\": \"Stephen F. Eisenman - Revolvy\", \"url\": \"https:\\/\\/www.revolvy.com\\/topic\\/Stephen%20F.%20Eisenman\", \"about\": [{\"name\": \"Stephen F. Eisenman\"}], \"isFamilyFriendly\": true, \"displayUrl\": \"https:\\/\\/www.revolvy.com\\/topic\\/Stephen F. Eisenman\", \"snippet\": \"Stephen F. Eisenman ... The only primary source for information about Stephen is the New Testament book ... it is understood as the fulfillment of an Old Testament ...\", \"dateLastCrawled\": \"2017-07-07T18:13:00.0000000Z\", \"language\": \"en\"}, {\"id\": \"https:\\/\\/api.cognitive.microsoft.com\\/api\\/v7\\/#WebPages.9\", \"name\": \"Champions for Christ - broom02.revolvy.com\", \"url\": \"https:\\/\\/broom02.revolvy.com\\/topic\\/Champions%20for%20Christ\", \"about\": [{\"name\": \"Champions for Christ\"}], \"isFamilyFriendly\": true, \"displayUrl\": \"https:\\/\\/broom02.revolvy.com\\/topic\\/Champions for Christ\", \"snippet\": \"Established in 1985 as part of the controversial Maranatha Campus Ministries , Champions for Christ ( CFC ) is an outreach to college and professional athletes. Now a part of the Every Nation group of ministries, CFC has also come under the auspices of other organizations since initial establishment.\", \"dateLastCrawled\": \"2018-02-24T22:01:00.0000000Z\", \"language\": \"en\"}]}, \"rankingResponse\": {\"mainline\": {\"items\": [{\"answerType\": \"WebPages\", \"resultIndex\": 0, \"value\": {\"id\": \"https:\\/\\/api.cognitive.microsoft.com\\/api\\/v7\\/#WebPages.0\"}}, {\"answerType\": \"WebPages\", \"resultIndex\": 1, \"value\": {\"id\": \"https:\\/\\/api.cognitive.microsoft.com\\/api\\/v7\\/#WebPages.1\"}}, {\"answerType\": \"WebPages\", \"resultIndex\": 2, \"value\": {\"id\": \"https:\\/\\/api.cognitive.microsoft.com\\/api\\/v7\\/#WebPages.2\"}}, {\"answerType\": \"WebPages\", \"resultIndex\": 3, \"value\": {\"id\": \"https:\\/\\/api.cognitive.microsoft.com\\/api\\/v7\\/#WebPages.3\"}}, {\"answerType\": \"WebPages\", \"resultIndex\": 4, \"value\": {\"id\": \"https:\\/\\/api.cognitive.microsoft.com\\/api\\/v7\\/#WebPages.4\"}}, {\"answerType\": \"WebPages\", \"resultIndex\": 5, \"value\": {\"id\": \"https:\\/\\/api.cognitive.microsoft.com\\/api\\/v7\\/#WebPages.5\"}}, {\"answerType\": \"WebPages\", \"resultIndex\": 6, \"value\": {\"id\": \"https:\\/\\/api.cognitive.microsoft.com\\/api\\/v7\\/#WebPages.6\"}}, {\"answerType\": \"WebPages\", \"resultIndex\": 7, \"value\": {\"id\": \"https:\\/\\/api.cognitive.microsoft.com\\/api\\/v7\\/#WebPages.7\"}}, {\"answerType\": \"WebPages\", \"resultIndex\": 8, \"value\": {\"id\": \"https:\\/\\/api.cognitive.microsoft.com\\/api\\/v7\\/#WebPages.8\"}}, {\"answerType\": \"WebPages\", \"resultIndex\": 9, \"value\": {\"id\": \"https:\\/\\/api.cognitive.microsoft.com\\/api\\/v7\\/#WebPages.9\"}}]}}}",
      "relevantHeaders": {
        "BingAPIs-TraceId": "9B924526D9304F9CB3AB81C13998EFAF",
        "BingAPIs-SessionId": "F04C094283CD41DDB88934F32C2B19E9",
        "X-MSEdge-ClientID": "385E2E192EA66C14050825D52F096D58",
        "BingAPIs-Market": "en-US",
        "X-MSEdge-Ref": "Ref A: 9B924526D9304F9CB3AB81C13998EFAF Ref B: BLUEDGE0419 Ref C: 2018-04-09T16:56:54Z"
      },
      "TotalResults": 11300
    },
    "SearchResultWithModifiedQuery": {
      "jsonResult": null,
      "relevantHeaders": null,
      "TotalResults": 0
    },
    "Attributes": []
  },
  "CasesData": {
    "1": {
      "Case": "Heart of Midlothian",
      "SearchResultWithQuestionPrepended": {
        "jsonResult": "{\"_type\": \"SearchResponse\", \"queryContext\": {\"originalQuery\": \"which football club has a stand displaying an extract from the nineteenth book of the old testament? Heart of Midlothian\"}, \"webPages\": {\"webSearchUrl\": \"https:\\/\\/www.bing.com\\/search?q=which+football+club+has+a+stand+displaying+an+extract+from+the+nineteenth+book+of+the+old+testament%3f+Heart+of+Midlothian\", \"totalEstimatedMatches\": 16300, \"value\": [{\"id\": \"https:\\/\\/api.cognitive.microsoft.com\\/api\\/v7\\/#WebPages.0\", \"name\": \"Game thread - 22nd February 2018, 9pm GMT : HQEurope\", \"url\": \"https:\\/\\/www.reddit.com\\/r\\/HQEurope\\/comments\\/7zhwbk\\/game_thread_22nd_february_2018_9pm_gmt\\/\", \"isFamilyFriendly\": true, \"displayUrl\": \"https:\\/\\/www.reddit.com\\/r\\/HQEurope\\/comments\\/7zhwbk\\/game_thread_22nd...\", \"snippet\": \"Playing somewhere interesting? Took a piece of the $750 pie? Caught out by a Savage Question? Discuss anything to do with tonight's game...\", \"dateLastCrawled\": \"2018-03-20T20:29:00.0000000Z\", \"language\": \"en\"}, {\"id\": \"https:\\/\\/api.cognitive.microsoft.com\\/api\\/v7\\/#WebPages.1\", \"name\": \"Tommy Walker (footballer, born 1915) - WikiVisually\", \"url\": \"https:\\/\\/wikivisually.com\\/wiki\\/Tommy_Walker_(footballer,_born_1915)\", \"isFamilyFriendly\": true, \"displayUrl\": \"https:\\/\\/wikivisually.com\\/wiki\\/Tommy_Walker_(footballer,_born_1915)\", \"snippet\": \"The first seeds of the Tommy Walker managerial ... Heart of Midlothian Football Club: ... It did however part of the Pentlands from Midlothian. The old county town ...\", \"dateLastCrawled\": \"2017-09-24T09:41:00.0000000Z\", \"language\": \"en\"}, {\"id\": \"https:\\/\\/api.cognitive.microsoft.com\\/api\\/v7\\/#WebPages.2\", \"name\": \"Dictionary.com's List of Every Word of the Year ...\", \"url\": \"http:\\/\\/www.dictionary.com\\/e\\/s\\/word-of-the-year-list\\/\", \"about\": [{\"name\": \"Word of the year\"}], \"isFamilyFriendly\": true, \"displayUrl\": \"www.dictionary.com\\/e\\/s\\/word-of-the-year-list\", \"snippet\": \"A list of every Word of the Year selection released by Dictionary.com. Dictionary.com's first Word of the Year was chosen in 2010.\", \"dateLastCrawled\": \"2018-04-05T15:43:00.0000000Z\", \"language\": \"en\"}, {\"id\": \"https:\\/\\/api.cognitive.microsoft.com\\/api\\/v7\\/#WebPages.3\", \"name\": \"List of Latin phrases (full) - Wikipedia\", \"url\": \"https:\\/\\/en.wikipedia.org\\/wiki\\/List_of_Latin_phrases_(full)\", \"isFamilyFriendly\": true, \"displayUrl\": \"https:\\/\\/en.wikipedia.org\\/wiki\\/List_of_Latin_phrases_(full)\", \"snippet\": \"This list is a combination of the twenty divided \\\"List of Latin phrases ... Or \\\"from the bottom of my heart\\\", ... Christ has freed us: title of volume I, book 5, ...\", \"dateLastCrawled\": \"2018-04-03T04:36:00.0000000Z\", \"language\": \"en\"}, {\"id\": \"https:\\/\\/api.cognitive.microsoft.com\\/api\\/v7\\/#WebPages.4\", \"name\": \"Gaelic in modern Scotland: View as single page\", \"url\": \"http:\\/\\/www.open.edu\\/openlearn\\/ocw\\/mod\\/oucontent\\/view.php?id=1960&printable=1\", \"isFamilyFriendly\": true, \"displayUrl\": \"www.open.edu\\/openlearn\\/ocw\\/mod\\/oucontent\\/view.php?id=1960&printable=1\", \"snippet\": \"Gaelic in modern Scotland ... The Scottish Gaelic New Testament was only completed in 1767 and the Old Testament in ... socialising in a club or pub or taking part ...\", \"dateLastCrawled\": \"2018-04-05T02:53:00.0000000Z\", \"language\": \"en\"}, {\"id\": \"https:\\/\\/api.cognitive.microsoft.com\\/api\\/v7\\/#WebPages.5\", \"name\": \"Hope Park Church, St Andrews - revolvy.com\", \"url\": \"https:\\/\\/www.revolvy.com\\/topic\\/Hope%20Park%20Church,%20St%20Andrews\", \"isFamilyFriendly\": true, \"displayUrl\": \"https:\\/\\/www.revolvy.com\\/topic\\/Hope Park Church, St Andrews\", \"snippet\": \"Hope Park Church, St Andrews in 2008. ... first in an old barn in Imrie's Close ... It has been the home ground of Birmingham City Football Club for more than a century.\", \"dateLastCrawled\": \"2017-06-10T06:13:00.0000000Z\", \"language\": \"en\"}, {\"id\": \"https:\\/\\/api.cognitive.microsoft.com\\/api\\/v7\\/#WebPages.6\", \"name\": \"1901 in Scotland | Revolvy\", \"url\": \"https:\\/\\/www.revolvy.com\\/main\\/index.php?s=1901%20in%20Scotland\", \"isFamilyFriendly\": true, \"displayUrl\": \"https:\\/\\/www.revolvy.com\\/main\\/index.php?s=1901 in Scotland\", \"snippet\": \"1901 in Scotland Events from the year 1901 in Scotland . ... 18 11 4 3 38 28 10 26 3 Heart of Midlothian 18 10 2 6 32 21 11 22 4 ... Scottish football club, ...\", \"dateLastCrawled\": \"2018-01-27T17:18:00.0000000Z\", \"language\": \"en\"}, {\"id\": \"https:\\/\\/api.cognitive.microsoft.com\\/api\\/v7\\/#WebPages.7\", \"name\": \"William McGregor (football) - WikiVisually\", \"url\": \"https:\\/\\/wikivisually.com\\/wiki\\/William_McGregor_(football)\", \"about\": [{\"name\": \"William McGregor\"}], \"isFamilyFriendly\": true, \"displayUrl\": \"https:\\/\\/wikivisually.com\\/wiki\\/William_McGregor_(football)\", \"snippet\": \"Famous past residents of Braco have included the founder of the Football League, William McGregor, ... Stand, North Stand. The club has ... Heart of Midlothian ...\", \"dateLastCrawled\": \"2018-03-19T08:36:00.0000000Z\", \"language\": \"en\"}, {\"id\": \"https:\\/\\/api.cognitive.microsoft.com\\/api\\/v7\\/#WebPages.8\", \"name\": \"SRA76 MARCH 2018 MASONIC MAGAZINE by Stewart Donaldson - issuu\", \"url\": \"https:\\/\\/issuu.com\\/sra76\\/docs\\/03_-_march_2018\", \"isFamilyFriendly\": true, \"displayUrl\": \"https:\\/\\/issuu.com\\/sra76\\/docs\\/03_-_march_2018\", \"snippet\": \"... SRA76 MARCH 2018 MASONIC MAGAZINE ... the God of the Old Testament is a God ... Showground and a former chairman of Heart of Midlothian Football Club.\", \"dateLastCrawled\": \"2018-03-26T16:54:00.0000000Z\", \"language\": \"en\"}, {\"id\": \"https:\\/\\/api.cognitive.microsoft.com\\/api\\/v7\\/#WebPages.9\", \"name\": \"The Project Gutenberg eBook of The Story of the Britannia ...\", \"url\": \"http:\\/\\/www.gutenberg.org\\/files\\/46788\\/46788-h\\/46788-h.htm\", \"isFamilyFriendly\": true, \"displayUrl\": \"www.gutenberg.org\\/files\\/46788\\/46788-h\\/46788-h.htm\", \"snippet\": \"The Project Gutenberg EBook of The Story of ... EARLY NINETEENTH CENTURY. From an old print in ... spend the time aloft with a book; many an hour has the present ...\", \"dateLastCrawled\": \"2016-09-01T15:54:00.0000000Z\", \"language\": \"en\"}]}, \"rankingResponse\": {\"mainline\": {\"items\": [{\"answerType\": \"WebPages\", \"resultIndex\": 0, \"value\": {\"id\": \"https:\\/\\/api.cognitive.microsoft.com\\/api\\/v7\\/#WebPages.0\"}}, {\"answerType\": \"WebPages\", \"resultIndex\": 1, \"value\": {\"id\": \"https:\\/\\/api.cognitive.microsoft.com\\/api\\/v7\\/#WebPages.1\"}}, {\"answerType\": \"WebPages\", \"resultIndex\": 2, \"value\": {\"id\": \"https:\\/\\/api.cognitive.microsoft.com\\/api\\/v7\\/#WebPages.2\"}}, {\"answerType\": \"WebPages\", \"resultIndex\": 3, \"value\": {\"id\": \"https:\\/\\/api.cognitive.microsoft.com\\/api\\/v7\\/#WebPages.3\"}}, {\"answerType\": \"WebPages\", \"resultIndex\": 4, \"value\": {\"id\": \"https:\\/\\/api.cognitive.microsoft.com\\/api\\/v7\\/#WebPages.4\"}}, {\"answerType\": \"WebPages\", \"resultIndex\": 5, \"value\": {\"id\": \"https:\\/\\/api.cognitive.microsoft.com\\/api\\/v7\\/#WebPages.5\"}}, {\"answerType\": \"WebPages\", \"resultIndex\": 6, \"value\": {\"id\": \"https:\\/\\/api.cognitive.microsoft.com\\/api\\/v7\\/#WebPages.6\"}}, {\"answerType\": \"WebPages\", \"resultIndex\": 7, \"value\": {\"id\": \"https:\\/\\/api.cognitive.microsoft.com\\/api\\/v7\\/#WebPages.7\"}}, {\"answerType\": \"WebPages\", \"resultIndex\": 8, \"value\": {\"id\": \"https:\\/\\/api.cognitive.microsoft.com\\/api\\/v7\\/#WebPages.8\"}}, {\"answerType\": \"WebPages\", \"resultIndex\": 9, \"value\": {\"id\": \"https:\\/\\/api.cognitive.microsoft.com\\/api\\/v7\\/#WebPages.9\"}}]}}}",
        "relevantHeaders": {
          "BingAPIs-TraceId": "CE0BBF2152734E079D4AC9BDF39C7F8D",
          "BingAPIs-SessionId": "AEF3B4964F0E4BD6B2E84AF7462D36BB",
          "X-MSEdge-ClientID": "2325A2C3B97D63992454A90FB8D26246",
          "BingAPIs-Market": "en-US",
          "X-MSEdge-Ref": "Ref A: CE0BBF2152734E079D4AC9BDF39C7F8D Ref B: BLUEDGE0306 Ref C: 2018-04-09T16:56:54Z"
        },
        "TotalResults": 16300
      },
      "SearchResultWithQuestionPrependedAndCaseInQuotes": {
        "jsonResult": "{\"_type\": \"SearchResponse\", \"queryContext\": {\"originalQuery\": \"which football club has a stand displaying an extract from the nineteenth book of the old testament? \\\"Heart of Midlothian\\\"\"}, \"webPages\": {\"webSearchUrl\": \"https:\\/\\/www.bing.com\\/search?q=which+football+club+has+a+stand+displaying+an+extract+from+the+nineteenth+book+of+the+old+testament%3f+%22Heart+of+Midlothian%22\", \"totalEstimatedMatches\": 13300, \"value\": [{\"id\": \"https:\\/\\/api.cognitive.microsoft.com\\/api\\/v7\\/#WebPages.0\", \"name\": \"Game thread - 22nd February 2018, 9pm GMT : HQEurope\", \"url\": \"https:\\/\\/www.reddit.com\\/r\\/HQEurope\\/comments\\/7zhwbk\\/game_thread_22nd_february_2018_9pm_gmt\\/\", \"isFamilyFriendly\": true, \"displayUrl\": \"https:\\/\\/www.reddit.com\\/r\\/HQEurope\\/comments\\/7zhwbk\\/game_thread_22nd...\", \"snippet\": \"Playing somewhere interesting? Took a piece of the $750 pie? Caught out by a Savage Question? Discuss anything to do with tonight's game...\", \"dateLastCrawled\": \"2018-03-20T20:29:00.0000000Z\", \"language\": \"en\"}, {\"id\": \"https:\\/\\/api.cognitive.microsoft.com\\/api\\/v7\\/#WebPages.1\", \"name\": \"English300 Flashcards | Quizlet\", \"url\": \"https:\\/\\/quizlet.com\\/1561632\\/english300-flash-cards\\/\", \"isFamilyFriendly\": true, \"displayUrl\": \"https:\\/\\/quizlet.com\\/1561632\\/english300-flash-cards\", \"snippet\": \"Start studying English300. Learn ... expressing or displaying one's warm and kindly feelings without ... 4 a short extract from a book or other printed ...\", \"dateLastCrawled\": \"2018-03-21T07:26:00.0000000Z\", \"language\": \"en\"}, {\"id\": \"https:\\/\\/api.cognitive.microsoft.com\\/api\\/v7\\/#WebPages.2\", \"name\": \"www.assumption.edu\", \"url\": \"http:\\/\\/www.assumption.edu\\/ahc\\/1920s\\/Eugenics\\/Klan.html\", \"about\": [{\"name\": \"Ku Klux Klan\"}], \"isFamilyFriendly\": true, \"displayUrl\": \"www.assumption.edu\\/ahc\\/1920s\\/Eugenics\\/Klan.html\", \"snippet\": \"We would like to show you a description here but the site won’t allow us.\", \"dateLastCrawled\": \"2018-03-14T20:31:00.0000000Z\", \"language\": \"en\"}, {\"id\": \"https:\\/\\/api.cognitive.microsoft.com\\/api\\/v7\\/#WebPages.3\", \"name\": \"Similar - Books on Google Play\", \"url\": \"https:\\/\\/play.google.com\\/store\\/books\\/collection\\/books_clusters_mrl_rt_BC436E48_AD6ACD28_0E3ED711\", \"isFamilyFriendly\": true, \"displayUrl\": \"https:\\/\\/play.google.com\\/store\\/books\\/collection\\/books_clusters_mrl...\", \"snippet\": \"Among the best known and most quoted books of the Old Testament, the Book of Psalms ... this little book that has ... new challenges—displaying ...\", \"dateLastCrawled\": \"2018-02-16T06:42:00.0000000Z\", \"language\": \"en\"}, {\"id\": \"https:\\/\\/api.cognitive.microsoft.com\\/api\\/v7\\/#WebPages.4\", \"name\": \"Dictionary.com's List of Every Word of the Year ...\", \"url\": \"http:\\/\\/www.dictionary.com\\/e\\/s\\/word-of-the-year-list\\/\", \"about\": [{\"name\": \"Word of the year\"}], \"isFamilyFriendly\": true, \"displayUrl\": \"www.dictionary.com\\/e\\/s\\/word-of-the-year-list\", \"snippet\": \"A list of every Word of the Year selection released by Dictionary.com. Dictionary.com's first Word of the Year was chosen in 2010.\", \"dateLastCrawled\": \"2018-04-05T15:43:00.0000000Z\", \"language\": \"en\"}, {\"id\": \"https:\\/\\/api.cognitive.microsoft.com\\/api\\/v7\\/#WebPages.5\", \"name\": \"Red - Wikipedia\", \"url\": \"https:\\/\\/en.wikipedia.org\\/wiki\\/Red_(color)\", \"about\": [{\"name\": \"Red\"}, {\"name\": \"Red\"}], \"isFamilyFriendly\": true, \"displayUrl\": \"https:\\/\\/en.wikipedia.org\\/wiki\\/Red_(color)\", \"snippet\": \"In the Old Testament of ... In club association football (soccer), red is a commonly ... and the sayings of Mao Zedong were published as a small red book in hundreds ...\", \"dateLastCrawled\": \"2018-04-04T01:34:00.0000000Z\", \"language\": \"en\"}, {\"id\": \"https:\\/\\/api.cognitive.microsoft.com\\/api\\/v7\\/#WebPages.6\", \"name\": \"The State - Online Library of Liberty\", \"url\": \"http:\\/\\/oll.libertyfund.org\\/titles\\/jasay-the-state\", \"isFamilyFriendly\": true, \"displayUrl\": \"oll.libertyfund.org\\/titles\\/jasay-the-state\", \"snippet\": \"Online Library of Liberty. ... While violence and preference may stand ... It is intuitively plausible that in a state of nature where people do not instantly club ...\", \"dateLastCrawled\": \"2018-03-27T09:19:00.0000000Z\", \"language\": \"en\"}, {\"id\": \"https:\\/\\/api.cognitive.microsoft.com\\/api\\/v7\\/#WebPages.7\", \"name\": \"The Project Gutenberg eBook of The Greatest English ...\", \"url\": \"http:\\/\\/www.gutenberg.org\\/files\\/40822\\/40822-h\\/40822-h.htm\", \"isFamilyFriendly\": true, \"displayUrl\": \"www.gutenberg.org\\/files\\/40822\\/40822-h\\/40822-h.htm\", \"snippet\": \"Project Gutenberg's The Greatest ... Most of the Old Testament then ... as the noblest and most beautiful Book in the world, which has exercised an ...\", \"dateLastCrawled\": \"2017-08-27T07:17:00.0000000Z\", \"language\": \"en\"}, {\"id\": \"https:\\/\\/api.cognitive.microsoft.com\\/api\\/v7\\/#WebPages.8\", \"name\": \"SRA76 MARCH 2018 MASONIC MAGAZINE by Stewart Donaldson - issuu\", \"url\": \"https:\\/\\/issuu.com\\/sra76\\/docs\\/03_-_march_2018\", \"isFamilyFriendly\": true, \"displayUrl\": \"https:\\/\\/issuu.com\\/sra76\\/docs\\/03_-_march_2018\", \"snippet\": \"... SRA76 MARCH 2018 MASONIC MAGAZINE ... the God of the Old Testament is a God ... Showground and a former chairman of Heart of Midlothian Football Club.\", \"dateLastCrawled\": \"2018-03-26T16:54:00.0000000Z\", \"language\": \"en\"}, {\"id\": \"https:\\/\\/api.cognitive.microsoft.com\\/api\\/v7\\/#WebPages.9\", \"name\": \"The Project Gutenberg eBook of Memoirs of My Dead Life, by ...\", \"url\": \"http:\\/\\/www.gutenberg.org\\/files\\/7789\\/7789-h\\/7789-h.htm\", \"isFamilyFriendly\": true, \"displayUrl\": \"www.gutenberg.org\\/files\\/7789\\/7789-h\\/7789-h.htm\", \"snippet\": \"The literary compliments he pays me and the interest that my book has excited ... out that in the Old Testament we are told ... the nineteenth century a great ...\", \"dateLastCrawled\": \"2017-12-28T19:33:00.0000000Z\", \"language\": \"en\"}]}, \"rankingResponse\": {\"mainline\": {\"items\": [{\"answerType\": \"WebPages\", \"resultIndex\": 0, \"value\": {\"id\": \"https:\\/\\/api.cognitive.microsoft.com\\/api\\/v7\\/#WebPages.0\"}}, {\"answerType\": \"WebPages\", \"resultIndex\": 1, \"value\": {\"id\": \"https:\\/\\/api.cognitive.microsoft.com\\/api\\/v7\\/#WebPages.1\"}}, {\"answerType\": \"WebPages\", \"resultIndex\": 2, \"value\": {\"id\": \"https:\\/\\/api.cognitive.microsoft.com\\/api\\/v7\\/#WebPages.2\"}}, {\"answerType\": \"WebPages\", \"resultIndex\": 3, \"value\": {\"id\": \"https:\\/\\/api.cognitive.microsoft.com\\/api\\/v7\\/#WebPages.3\"}}, {\"answerType\": \"WebPages\", \"resultIndex\": 4, \"value\": {\"id\": \"https:\\/\\/api.cognitive.microsoft.com\\/api\\/v7\\/#WebPages.4\"}}, {\"answerType\": \"WebPages\", \"resultIndex\": 5, \"value\": {\"id\": \"https:\\/\\/api.cognitive.microsoft.com\\/api\\/v7\\/#WebPages.5\"}}, {\"answerType\": \"WebPages\", \"resultIndex\": 6, \"value\": {\"id\": \"https:\\/\\/api.cognitive.microsoft.com\\/api\\/v7\\/#WebPages.6\"}}, {\"answerType\": \"WebPages\", \"resultIndex\": 7, \"value\": {\"id\": \"https:\\/\\/api.cognitive.microsoft.com\\/api\\/v7\\/#WebPages.7\"}}, {\"answerType\": \"WebPages\", \"resultIndex\": 8, \"value\": {\"id\": \"https:\\/\\/api.cognitive.microsoft.com\\/api\\/v7\\/#WebPages.8\"}}, {\"answerType\": \"WebPages\", \"resultIndex\": 9, \"value\": {\"id\": \"https:\\/\\/api.cognitive.microsoft.com\\/api\\/v7\\/#WebPages.9\"}}]}}}",
        "relevantHeaders": {
          "BingAPIs-TraceId": "89D770B8DB674610ABCDCA4A67663792",
          "BingAPIs-SessionId": "7F1F036E97B442DFADAC73C59617F36C",
          "X-MSEdge-ClientID": "32F458C82F096C9F0A0053042EA66DA2",
          "BingAPIs-Market": "en-US",
          "X-MSEdge-Ref": "Ref A: 89D770B8DB674610ABCDCA4A67663792 Ref B: BLUEDGE0320 Ref C: 2018-04-09T16:56:54Z"
        },
        "TotalResults": 13300
      },
      "TimesMentionedInQuestionSearchResult": 0,
      "Attributes": null,
      "IsCorrect": false
    },
    "2": {
      "Case": "Wigan Athletic",
      "SearchResultWithQuestionPrepended": {
        "jsonResult": "{\"_type\": \"SearchResponse\", \"queryContext\": {\"originalQuery\": \"which football club has a stand displaying an extract from the nineteenth book of the old testament? Wigan Athletic\"}, \"webPages\": {\"webSearchUrl\": \"https:\\/\\/www.bing.com\\/search?q=which+football+club+has+a+stand+displaying+an+extract+from+the+nineteenth+book+of+the+old+testament%3f+Wigan+Athletic\", \"totalEstimatedMatches\": 29600, \"value\": [{\"id\": \"https:\\/\\/api.cognitive.microsoft.com\\/api\\/v7\\/#WebPages.0\", \"name\": \"Game thread - 22nd February 2018, 9pm GMT : HQEurope\", \"url\": \"https:\\/\\/www.reddit.com\\/r\\/HQEurope\\/comments\\/7zhwbk\\/game_thread_22nd_february_2018_9pm_gmt\\/\", \"isFamilyFriendly\": true, \"displayUrl\": \"https:\\/\\/www.reddit.com\\/r\\/HQEurope\\/comments\\/7zhwbk\\/game_thread_22nd...\", \"snippet\": \"Playing somewhere interesting? Took a piece of the $750 pie? Caught out by a Savage Question? Discuss anything to do with tonight's game...\", \"dateLastCrawled\": \"2018-03-20T20:29:00.0000000Z\", \"language\": \"en\"}, {\"id\": \"https:\\/\\/api.cognitive.microsoft.com\\/api\\/v7\\/#WebPages.1\", \"name\": \"Dunfermline Athletic F.C. - WikiVisually\", \"url\": \"https:\\/\\/wikivisually.com\\/wiki\\/Dunfermline_Athletic_F.C.\", \"about\": [{\"name\": \"Dunfermline Athletic F.C.\"}], \"isFamilyFriendly\": true, \"displayUrl\": \"https:\\/\\/wikivisually.com\\/wiki\\/Dunfermline_Athletic_F.C.\", \"snippet\": \"The entire wikipedia with video and photo galleries for each article. Find something interesting to watch in seconds.\", \"dateLastCrawled\": \"2017-11-20T21:19:00.0000000Z\", \"language\": \"en\"}, {\"id\": \"https:\\/\\/api.cognitive.microsoft.com\\/api\\/v7\\/#WebPages.2\", \"name\": \"HanesCymru | 100 Years of Swansea City FC\", \"url\": \"https:\\/\\/swans100.com\\/author\\/martinjohnes\\/\", \"isFamilyFriendly\": true, \"displayUrl\": \"https:\\/\\/swans100.com\\/author\\/martinjohnes\", \"snippet\": \"That was the place where youngsters yearned to be old enough to stand, ... Swansea City v Wigan Athletic ... This enabled the Football Club to take out a ...\", \"dateLastCrawled\": \"2018-02-13T11:34:00.0000000Z\", \"language\": \"en\"}, {\"id\": \"https:\\/\\/api.cognitive.microsoft.com\\/api\\/v7\\/#WebPages.3\", \"name\": \"Manchester United F.C. - WikiVisually.com\", \"url\": \"https:\\/\\/wikivisually.com\\/wiki\\/Manchester_United_F.C\", \"isFamilyFriendly\": true, \"displayUrl\": \"https:\\/\\/wikivisually.com\\/wiki\\/Manchester_United_F.C\", \"snippet\": \"Manchester United Football Club is a professional football club based at Old Trafford, Greater Manchester, England, that competes in the Premier League, the top flight of English\", \"dateLastCrawled\": \"2017-11-13T15:57:00.0000000Z\", \"language\": \"en\"}, {\"id\": \"https:\\/\\/api.cognitive.microsoft.com\\/api\\/v7\\/#WebPages.4\", \"name\": \"Charles Tylor | Revolvy\", \"url\": \"https:\\/\\/www.revolvy.com\\/main\\/index.php?s=Charles%20Tylor\", \"isFamilyFriendly\": true, \"displayUrl\": \"https:\\/\\/www.revolvy.com\\/main\\/index.php?s=Charles Tylor\", \"snippet\": \"The Old Testament as seen from the New \\/ Charles ... a book that has been called a \\\"major contribution to the history of ... Wigan Athletic Football Club () ...\", \"dateLastCrawled\": \"2018-03-26T03:45:00.0000000Z\", \"language\": \"en\"}, {\"id\": \"https:\\/\\/api.cognitive.microsoft.com\\/api\\/v7\\/#WebPages.5\", \"name\": \"Grassroots Magazine by Paul McGhee - issuu\", \"url\": \"https:\\/\\/issuu.com\\/mcghee84\\/docs\\/grassroots_magazine\", \"isFamilyFriendly\": true, \"displayUrl\": \"https:\\/\\/issuu.com\\/mcghee84\\/docs\\/grassroots_magazine\", \"snippet\": \"James McFadden on his youth career, that night in Paris and our top 5 youth goals. A PUBLICATION BY. NE. A FULL JOMA KIT FOR YOUR TEAM COURTESY OF FOOTBALL NATION!\", \"dateLastCrawled\": \"2018-03-31T04:30:00.0000000Z\", \"language\": \"en\"}, {\"id\": \"https:\\/\\/api.cognitive.microsoft.com\\/api\\/v7\\/#WebPages.6\", \"name\": \"Issue 55: August - November 2010 by Inspiring healthy ...\", \"url\": \"https:\\/\\/issuu.com\\/wlct\\/docs\\/pf55\", \"isFamilyFriendly\": true, \"displayUrl\": \"https:\\/\\/issuu.com\\/wlct\\/docs\\/pf55\", \"snippet\": \"Produced by Wigan Heritage Service. Issue No. 55. August - November 2010. Football Fever. YOUR HERITAGE. ÂŁ1\", \"dateLastCrawled\": \"2018-04-01T04:58:00.0000000Z\", \"language\": \"en\"}, {\"id\": \"https:\\/\\/api.cognitive.microsoft.com\\/api\\/v7\\/#WebPages.7\", \"name\": \"Uncategorized | 100 Years of Swansea City FC\", \"url\": \"https:\\/\\/swans100.com\\/category\\/uncategorized\\/\", \"isFamilyFriendly\": true, \"displayUrl\": \"https:\\/\\/swans100.com\\/category\\/uncategorized\", \"snippet\": \"... Johns would provide a link between the Football Club and the panto with ... v Wigan Athletic 12 ... Wing Stand’ (which still has its ...\", \"dateLastCrawled\": \"2018-02-12T17:51:00.0000000Z\", \"language\": \"en\"}, {\"id\": \"https:\\/\\/api.cognitive.microsoft.com\\/api\\/v7\\/#WebPages.8\", \"name\": \"Caleb Daniel - Revolvy\", \"url\": \"https:\\/\\/topics.revolvy.com\\/topic\\/Caleb%20Daniel\", \"isFamilyFriendly\": true, \"displayUrl\": \"https:\\/\\/topics.revolvy.com\\/topic\\/Caleb Daniel\", \"snippet\": \"Caleb Daniel (born 7 July 1996 ... is a professional Australian rules footballer playing for the Carlton Football Club in the ... Wigan Athletic After a series of ...\", \"dateLastCrawled\": \"2017-11-04T22:26:00.0000000Z\", \"language\": \"en\"}, {\"id\": \"https:\\/\\/api.cognitive.microsoft.com\\/api\\/v7\\/#WebPages.9\", \"name\": \"Dictionary.com's List of Every Word of the Year ...\", \"url\": \"http:\\/\\/www.dictionary.com\\/e\\/s\\/word-of-the-year-list\\/\", \"about\": [{\"name\": \"Word of the year\"}], \"isFamilyFriendly\": true, \"displayUrl\": \"www.dictionary.com\\/e\\/s\\/word-of-the-year-list\", \"snippet\": \"A list of every Word of the Year selection released by Dictionary.com. Dictionary.com's first Word of the Year was chosen in 2010.\", \"dateLastCrawled\": \"2018-04-05T15:43:00.0000000Z\", \"language\": \"en\"}]}, \"rankingResponse\": {\"mainline\": {\"items\": [{\"answerType\": \"WebPages\", \"resultIndex\": 0, \"value\": {\"id\": \"https:\\/\\/api.cognitive.microsoft.com\\/api\\/v7\\/#WebPages.0\"}}, {\"answerType\": \"WebPages\", \"resultIndex\": 1, \"value\": {\"id\": \"https:\\/\\/api.cognitive.microsoft.com\\/api\\/v7\\/#WebPages.1\"}}, {\"answerType\": \"WebPages\", \"resultIndex\": 2, \"value\": {\"id\": \"https:\\/\\/api.cognitive.microsoft.com\\/api\\/v7\\/#WebPages.2\"}}, {\"answerType\": \"WebPages\", \"resultIndex\": 3, \"value\": {\"id\": \"https:\\/\\/api.cognitive.microsoft.com\\/api\\/v7\\/#WebPages.3\"}}, {\"answerType\": \"WebPages\", \"resultIndex\": 4, \"value\": {\"id\": \"https:\\/\\/api.cognitive.microsoft.com\\/api\\/v7\\/#WebPages.4\"}}, {\"answerType\": \"WebPages\", \"resultIndex\": 5, \"value\": {\"id\": \"https:\\/\\/api.cognitive.microsoft.com\\/api\\/v7\\/#WebPages.5\"}}, {\"answerType\": \"WebPages\", \"resultIndex\": 6, \"value\": {\"id\": \"https:\\/\\/api.cognitive.microsoft.com\\/api\\/v7\\/#WebPages.6\"}}, {\"answerType\": \"WebPages\", \"resultIndex\": 7, \"value\": {\"id\": \"https:\\/\\/api.cognitive.microsoft.com\\/api\\/v7\\/#WebPages.7\"}}, {\"answerType\": \"WebPages\", \"resultIndex\": 8, \"value\": {\"id\": \"https:\\/\\/api.cognitive.microsoft.com\\/api\\/v7\\/#WebPages.8\"}}, {\"answerType\": \"WebPages\", \"resultIndex\": 9, \"value\": {\"id\": \"https:\\/\\/api.cognitive.microsoft.com\\/api\\/v7\\/#WebPages.9\"}}]}}}",
        "relevantHeaders": {
          "BingAPIs-TraceId": "0955E83018B64451BBB20881020F8E7C",
          "BingAPIs-SessionId": "5F27B1D422F34086B3A8B8C225F4C09A",
          "X-MSEdge-ClientID": "330E0593618865EE00850E5F602764B5",
          "BingAPIs-Market": "en-US",
          "X-MSEdge-Ref": "Ref A: 0955E83018B64451BBB20881020F8E7C Ref B: BLUEDGE0507 Ref C: 2018-04-09T16:56:54Z"
        },
        "TotalResults": 29600
      },
      "SearchResultWithQuestionPrependedAndCaseInQuotes": {
        "jsonResult": "{\"_type\": \"SearchResponse\", \"queryContext\": {\"originalQuery\": \"which football club has a stand displaying an extract from the nineteenth book of the old testament? \\\"Wigan Athletic\\\"\"}, \"webPages\": {\"webSearchUrl\": \"https:\\/\\/www.bing.com\\/search?q=which+football+club+has+a+stand+displaying+an+extract+from+the+nineteenth+book+of+the+old+testament%3f+%22Wigan+Athletic%22\", \"totalEstimatedMatches\": 27700, \"value\": [{\"id\": \"https:\\/\\/api.cognitive.microsoft.com\\/api\\/v7\\/#WebPages.0\", \"name\": \"Game thread - 22nd February 2018, 9pm GMT : HQEurope\", \"url\": \"https:\\/\\/www.reddit.com\\/r\\/HQEurope\\/comments\\/7zhwbk\\/game_thread_22nd_february_2018_9pm_gmt\\/\", \"isFamilyFriendly\": true, \"displayUrl\": \"https:\\/\\/www.reddit.com\\/r\\/HQEurope\\/comments\\/7zhwbk\\/game_thread_22nd...\", \"snippet\": \"Playing somewhere interesting? Took a piece of the $750 pie? Caught out by a Savage Question? Discuss anything to do with tonight's game...\", \"dateLastCrawled\": \"2018-03-20T20:29:00.0000000Z\", \"language\": \"en\"}, {\"id\": \"https:\\/\\/api.cognitive.microsoft.com\\/api\\/v7\\/#WebPages.1\", \"name\": \"English300 Flashcards | Quizlet\", \"url\": \"https:\\/\\/quizlet.com\\/1561632\\/english300-flash-cards\\/\", \"isFamilyFriendly\": true, \"displayUrl\": \"https:\\/\\/quizlet.com\\/1561632\\/english300-flash-cards\", \"snippet\": \"Start studying English300. Learn ... expressing or displaying one's warm and kindly feelings without ... 4 a short extract from a book or other printed ...\", \"dateLastCrawled\": \"2018-03-21T07:26:00.0000000Z\", \"language\": \"en\"}, {\"id\": \"https:\\/\\/api.cognitive.microsoft.com\\/api\\/v7\\/#WebPages.2\", \"name\": \"The Story of My Life. - digital.library.upenn.edu\", \"url\": \"http:\\/\\/digital.library.upenn.edu\\/women\\/keller\\/life\\/life.html\", \"about\": [{\"name\": \"Helen Keller\"}, {\"name\": \"The Story of My Life\"}], \"isFamilyFriendly\": true, \"displayUrl\": \"digital.library.upenn.edu\\/women\\/keller\\/life\\/life.html\", \"snippet\": \"A few impressions stand out vividly ... You enjoy with all your soul the sweet thunder of the Old Testament ... We must extract them from the crannied wall of ...\", \"dateLastCrawled\": \"2018-04-05T00:01:00.0000000Z\", \"language\": \"en\"}, {\"id\": \"https:\\/\\/api.cognitive.microsoft.com\\/api\\/v7\\/#WebPages.3\", \"name\": \"Similar - Books on Google Play\", \"url\": \"https:\\/\\/play.google.com\\/store\\/books\\/collection\\/books_clusters_mrl_rt_BC436E48_AD6ACD28_0E3ED711\", \"isFamilyFriendly\": true, \"displayUrl\": \"https:\\/\\/play.google.com\\/store\\/books\\/collection\\/books_clusters_mrl...\", \"snippet\": \"Among the best known and most quoted books of the Old Testament, the Book of Psalms ... Patriots football team and ... in this little book that has been ...\", \"dateLastCrawled\": \"2018-02-16T06:42:00.0000000Z\", \"language\": \"en\"}, {\"id\": \"https:\\/\\/api.cognitive.microsoft.com\\/api\\/v7\\/#WebPages.4\", \"name\": \"Studying religion: View as single page - Open University\", \"url\": \"http:\\/\\/www.open.edu\\/openlearn\\/ocw\\/mod\\/oucontent\\/view.php?id=1601&printable=1\", \"isFamilyFriendly\": true, \"displayUrl\": \"www.open.edu\\/openlearn\\/ocw\\/mod\\/oucontent\\/view.php?id=1601&printable=1\", \"snippet\": \"Studying religion Introduction. This ... parallels between following a football club and following a ... is to be found in the first five books of the Christian Old ...\", \"dateLastCrawled\": \"2018-03-18T16:41:00.0000000Z\", \"language\": \"en\"}, {\"id\": \"https:\\/\\/api.cognitive.microsoft.com\\/api\\/v7\\/#WebPages.5\", \"name\": \"Red - Wikipedia\", \"url\": \"https:\\/\\/en.wikipedia.org\\/wiki\\/Red_(color)\", \"about\": [{\"name\": \"Red\"}, {\"name\": \"Red\"}], \"isFamilyFriendly\": true, \"displayUrl\": \"https:\\/\\/en.wikipedia.org\\/wiki\\/Red_(color)\", \"snippet\": \"Red has been an important color in Chinese ... In the Old Testament of the Bible, ... In club association football (soccer), red is a commonly used color throughout ...\", \"dateLastCrawled\": \"2018-04-04T01:34:00.0000000Z\", \"language\": \"en\"}, {\"id\": \"https:\\/\\/api.cognitive.microsoft.com\\/api\\/v7\\/#WebPages.6\", \"name\": \"Edge.org\", \"url\": \"https:\\/\\/www.edge.org\\/responses\\/q2013\", \"isFamilyFriendly\": true, \"displayUrl\": \"https:\\/\\/www.edge.org\\/responses\\/q2013\", \"snippet\": \"To arrive at the edge of the world's knowledge, seek out the most complex and sophisticated minds, put them in a room together, and have them ask each other the questions they are asking themselves.\", \"dateLastCrawled\": \"2018-04-04T13:32:00.0000000Z\", \"language\": \"en\"}, {\"id\": \"https:\\/\\/api.cognitive.microsoft.com\\/api\\/v7\\/#WebPages.7\", \"name\": \"The Project Gutenberg eBook of The Story of the Britannia ...\", \"url\": \"http:\\/\\/www.gutenberg.org\\/files\\/46788\\/46788-h\\/46788-h.htm\", \"isFamilyFriendly\": true, \"displayUrl\": \"www.gutenberg.org\\/files\\/46788\\/46788-h\\/46788-h.htm\", \"snippet\": \"The Project Gutenberg EBook of The Story of ... EARLY NINETEENTH CENTURY. From an old print in ... spend the time aloft with a book; many an hour has the present ...\", \"dateLastCrawled\": \"2016-09-01T15:54:00.0000000Z\", \"language\": \"en\"}, {\"id\": \"https:\\/\\/api.cognitive.microsoft.com\\/api\\/v7\\/#WebPages.8\", \"name\": \"Dictionary.com's List of Every Word of the Year ...\", \"url\": \"http:\\/\\/www.dictionary.com\\/e\\/s\\/word-of-the-year-list\\/\", \"about\": [{\"name\": \"Word of the year\"}], \"isFamilyFriendly\": true, \"displayUrl\": \"www.dictionary.com\\/e\\/s\\/word-of-the-year-list\", \"snippet\": \"A list of every Word of the Year selection released by Dictionary.com. Dictionary.com's first Word of the Year was chosen in 2010.\", \"dateLastCrawled\": \"2018-04-05T15:43:00.0000000Z\", \"language\": \"en\"}, {\"id\": \"https:\\/\\/api.cognitive.microsoft.com\\/api\\/v7\\/#WebPages.9\", \"name\": \"List of atheist authors - Wikipedia\", \"url\": \"https:\\/\\/en.wikipedia.org\\/wiki\\/List_of_atheist_authors\", \"isFamilyFriendly\": true, \"displayUrl\": \"https:\\/\\/en.wikipedia.org\\/wiki\\/List_of_atheist_authors\", \"snippet\": \"This is a list of atheist authors. ... author of atheistic Testament of Man series. ... on display at Israel's Holocaust museum, she has been dubbed the \\\"Polish ...\", \"dateLastCrawled\": \"2018-04-02T03:04:00.0000000Z\", \"language\": \"en\"}]}, \"rankingResponse\": {\"mainline\": {\"items\": [{\"answerType\": \"WebPages\", \"resultIndex\": 0, \"value\": {\"id\": \"https:\\/\\/api.cognitive.microsoft.com\\/api\\/v7\\/#WebPages.0\"}}, {\"answerType\": \"WebPages\", \"resultIndex\": 1, \"value\": {\"id\": \"https:\\/\\/api.cognitive.microsoft.com\\/api\\/v7\\/#WebPages.1\"}}, {\"answerType\": \"WebPages\", \"resultIndex\": 2, \"value\": {\"id\": \"https:\\/\\/api.cognitive.microsoft.com\\/api\\/v7\\/#WebPages.2\"}}, {\"answerType\": \"WebPages\", \"resultIndex\": 3, \"value\": {\"id\": \"https:\\/\\/api.cognitive.microsoft.com\\/api\\/v7\\/#WebPages.3\"}}, {\"answerType\": \"WebPages\", \"resultIndex\": 4, \"value\": {\"id\": \"https:\\/\\/api.cognitive.microsoft.com\\/api\\/v7\\/#WebPages.4\"}}, {\"answerType\": \"WebPages\", \"resultIndex\": 5, \"value\": {\"id\": \"https:\\/\\/api.cognitive.microsoft.com\\/api\\/v7\\/#WebPages.5\"}}, {\"answerType\": \"WebPages\", \"resultIndex\": 6, \"value\": {\"id\": \"https:\\/\\/api.cognitive.microsoft.com\\/api\\/v7\\/#WebPages.6\"}}, {\"answerType\": \"WebPages\", \"resultIndex\": 7, \"value\": {\"id\": \"https:\\/\\/api.cognitive.microsoft.com\\/api\\/v7\\/#WebPages.7\"}}, {\"answerType\": \"WebPages\", \"resultIndex\": 8, \"value\": {\"id\": \"https:\\/\\/api.cognitive.microsoft.com\\/api\\/v7\\/#WebPages.8\"}}, {\"answerType\": \"WebPages\", \"resultIndex\": 9, \"value\": {\"id\": \"https:\\/\\/api.cognitive.microsoft.com\\/api\\/v7\\/#WebPages.9\"}}]}}}",
        "relevantHeaders": {
          "BingAPIs-TraceId": "7B56233EFB22405DB8133276024EAE83",
          "BingAPIs-SessionId": "D44CBB4ACA0949FCB9B6D39F6F6268A7",
          "X-MSEdge-ClientID": "1EF7714690756C9B03B77A8A91DA6D26",
          "BingAPIs-Market": "en-US",
          "X-MSEdge-Ref": "Ref A: 7B56233EFB22405DB8133276024EAE83 Ref B: BLUEDGE0517 Ref C: 2018-04-09T16:56:55Z"
        },
        "TotalResults": 27700
      },
      "TimesMentionedInQuestionSearchResult": 0,
      "Attributes": null,
      "IsCorrect": false
    },
    "3": {
      "Case": "West Bromwich Albion",
      "SearchResultWithQuestionPrepended": {
        "jsonResult": "{\"_type\": \"SearchResponse\", \"queryContext\": {\"originalQuery\": \"which football club has a stand displaying an extract from the nineteenth book of the old testament? West Bromwich Albion\"}, \"webPages\": {\"webSearchUrl\": \"https:\\/\\/www.bing.com\\/search?q=which+football+club+has+a+stand+displaying+an+extract+from+the+nineteenth+book+of+the+old+testament%3f+West+Bromwich+Albion\", \"totalEstimatedMatches\": 26000, \"value\": [{\"id\": \"https:\\/\\/api.cognitive.microsoft.com\\/api\\/v7\\/#WebPages.0\", \"name\": \"Game thread - 22nd February 2018, 9pm GMT : HQEurope\", \"url\": \"https:\\/\\/www.reddit.com\\/r\\/HQEurope\\/comments\\/7zhwbk\\/game_thread_22nd_february_2018_9pm_gmt\\/\", \"isFamilyFriendly\": true, \"displayUrl\": \"https:\\/\\/www.reddit.com\\/r\\/HQEurope\\/comments\\/7zhwbk\\/game_thread_22nd...\", \"snippet\": \"Playing somewhere interesting? Took a piece of the $750 pie? Caught out by a Savage Question? Discuss anything to do with tonight's game...\", \"dateLastCrawled\": \"2018-03-20T20:29:00.0000000Z\", \"language\": \"en\"}, {\"id\": \"https:\\/\\/api.cognitive.microsoft.com\\/api\\/v7\\/#WebPages.1\", \"name\": \"1902–03 Blackpool F.C. season - WikiVisually\", \"url\": \"https:\\/\\/wikivisually.com\\/wiki\\/1902%E2%80%9303_Blackpool_F.C._season\", \"isFamilyFriendly\": true, \"displayUrl\": \"https:\\/\\/wikivisually.com\\/wiki\\/1902–03_Blackpool_F.C._season\", \"snippet\": \"... they would reach the 1912 FA Cup Final where they would defeat West Bromwich Albion 1 ... the old West Stand was ... football. The club has won ...\", \"dateLastCrawled\": \"2018-02-25T11:20:00.0000000Z\", \"language\": \"en\"}, {\"id\": \"https:\\/\\/api.cognitive.microsoft.com\\/api\\/v7\\/#WebPages.2\", \"name\": \"\\\"Norwich and Peterborough Building Society\\\" on Revolvy.com\", \"url\": \"https:\\/\\/update.revolvy.com\\/topic\\/Norwich%20and%20Peterborough%20Building%20Society\", \"isFamilyFriendly\": true, \"displayUrl\": \"https:\\/\\/update.revolvy.com\\/topic\\/Norwich and Peterborough Building...\", \"snippet\": \"The Society has over 45 branch offices mainly located in East Anglia and the surrounding counties of ... Norwich and Peterborough Building Society . ... West ...\", \"dateLastCrawled\": \"2017-10-21T22:04:00.0000000Z\", \"language\": \"en\"}, {\"id\": \"https:\\/\\/api.cognitive.microsoft.com\\/api\\/v7\\/#WebPages.3\", \"name\": \"William McGregor (football) - WikiVisually\", \"url\": \"https:\\/\\/wikivisually.com\\/wiki\\/William_McGregor_(football)\", \"about\": [{\"name\": \"William McGregor\"}], \"isFamilyFriendly\": true, \"displayUrl\": \"https:\\/\\/wikivisually.com\\/wiki\\/William_McGregor_(football)\", \"snippet\": \"... including the FA Cup finalists West Bromwich Albion ... Official website Old Etonians at the Football Club ... Trinity Road Stand, North Stand. The club has ...\", \"dateLastCrawled\": \"2018-03-19T08:36:00.0000000Z\", \"language\": \"en\"}, {\"id\": \"https:\\/\\/api.cognitive.microsoft.com\\/api\\/v7\\/#WebPages.4\", \"name\": \"Dictionary.com's List of Every Word of the Year ...\", \"url\": \"http:\\/\\/www.dictionary.com\\/e\\/s\\/word-of-the-year-list\\/\", \"about\": [{\"name\": \"Word of the year\"}], \"isFamilyFriendly\": true, \"displayUrl\": \"www.dictionary.com\\/e\\/s\\/word-of-the-year-list\", \"snippet\": \"A list of every Word of the Year selection released by Dictionary.com. Dictionary.com's first Word of the Year was chosen in 2010.\", \"dateLastCrawled\": \"2018-04-05T15:43:00.0000000Z\", \"language\": \"en\"}, {\"id\": \"https:\\/\\/api.cognitive.microsoft.com\\/api\\/v7\\/#WebPages.5\", \"name\": \"Red Leicester - Revolvy\", \"url\": \"https:\\/\\/topics.revolvy.com\\/topic\\/Red%20Leicester&item_type=topic\", \"isFamilyFriendly\": true, \"displayUrl\": \"https:\\/\\/topics.revolvy.com\\/topic\\/Red Leicester&item_type=topic\", \"snippet\": \"Although Red Leicester can be young or \\\"old\\\", ... Since the 18th century it has been coloured orange by adding annatto extract during manufacture. [2]\", \"dateLastCrawled\": \"2017-10-02T17:44:00.0000000Z\", \"language\": \"en\"}, {\"id\": \"https:\\/\\/api.cognitive.microsoft.com\\/api\\/v7\\/#WebPages.6\", \"name\": \"Business Direction 15 by Distinctive Publishing - issuu\", \"url\": \"https:\\/\\/issuu.com\\/distinctivepublishing\\/docs\\/bd15_issuu\", \"isFamilyFriendly\": true, \"displayUrl\": \"https:\\/\\/issuu.com\\/distinctivepublishing\\/docs\\/bd15_issuu\", \"snippet\": \"... Business Direction 15, ... the kudos of West Bromwich Albion Football Club to make a ... stats displaying your results. Business Direction published by ...\", \"dateLastCrawled\": \"2018-04-02T07:49:00.0000000Z\", \"language\": \"en\"}, {\"id\": \"https:\\/\\/api.cognitive.microsoft.com\\/api\\/v7\\/#WebPages.7\", \"name\": \"Conociendo el Reino Unido – laescueladeingles\", \"url\": \"https:\\/\\/laescueladeingles.wordpress.com\\/category\\/conociendo-el-reino-unido\\/\", \"isFamilyFriendly\": true, \"displayUrl\": \"https:\\/\\/laescueladeingles.wordpress.com\\/...\\/conociendo-el-reino-unido\", \"snippet\": \"Another Premier League club, West Bromwich Albion F ... world for the football rivalry of the Old Firm ... stand as a testament to the great wealth in ...\", \"dateLastCrawled\": \"2018-03-20T21:52:00.0000000Z\", \"language\": \"en\"}, {\"id\": \"https:\\/\\/api.cognitive.microsoft.com\\/api\\/v7\\/#WebPages.8\", \"name\": \"BQ West Midlands Autumn 2015 by BQ Magazine - issuu\", \"url\": \"https:\\/\\/issuu.com\\/room501\\/docs\\/bqwm_aut15interactivenew\", \"isFamilyFriendly\": true, \"displayUrl\": \"https:\\/\\/issuu.com\\/room501\\/docs\\/bqwm_aut15interactivenew\", \"snippet\": \"BUSINESS QUARTER. BUSINESS QUARTER. West Midlands: Autumn 2015. Exploring our canals. Bottling success Old business in a new age. Live debate. Security in the cyber age\", \"dateLastCrawled\": \"2018-02-25T09:35:00.0000000Z\", \"language\": \"en\"}, {\"id\": \"https:\\/\\/api.cognitive.microsoft.com\\/api\\/v7\\/#WebPages.9\", \"name\": \"100 GREAT THINGS ABOUT THE WEST MIDLANDS; Sponsored by The ...\", \"url\": \"https:\\/\\/www.thefreelibrary.com\\/100+GREAT+THINGS+ABOUT+THE+WEST+MIDLANDS%3b+Sponsored+by+The+Heart+of...-a0185694169\", \"isFamilyFriendly\": true, \"displayUrl\": \"https:\\/\\/www.thefreelibrary.com\\/100+GREAT+THINGS+ABOUT+THE+WEST...\", \"snippet\": \"100 GREAT THINGS ABOUT THE WEST ... the title Birmingham Football Club when it ... beaten 2-1 by rivals West Bromwich Albion and after years of ...\", \"dateLastCrawled\": \"2017-10-28T21:39:00.0000000Z\", \"language\": \"en\"}]}, \"rankingResponse\": {\"mainline\": {\"items\": [{\"answerType\": \"WebPages\", \"resultIndex\": 0, \"value\": {\"id\": \"https:\\/\\/api.cognitive.microsoft.com\\/api\\/v7\\/#WebPages.0\"}}, {\"answerType\": \"WebPages\", \"resultIndex\": 1, \"value\": {\"id\": \"https:\\/\\/api.cognitive.microsoft.com\\/api\\/v7\\/#WebPages.1\"}}, {\"answerType\": \"WebPages\", \"resultIndex\": 2, \"value\": {\"id\": \"https:\\/\\/api.cognitive.microsoft.com\\/api\\/v7\\/#WebPages.2\"}}, {\"answerType\": \"WebPages\", \"resultIndex\": 3, \"value\": {\"id\": \"https:\\/\\/api.cognitive.microsoft.com\\/api\\/v7\\/#WebPages.3\"}}, {\"answerType\": \"WebPages\", \"resultIndex\": 4, \"value\": {\"id\": \"https:\\/\\/api.cognitive.microsoft.com\\/api\\/v7\\/#WebPages.4\"}}, {\"answerType\": \"WebPages\", \"resultIndex\": 5, \"value\": {\"id\": \"https:\\/\\/api.cognitive.microsoft.com\\/api\\/v7\\/#WebPages.5\"}}, {\"answerType\": \"WebPages\", \"resultIndex\": 6, \"value\": {\"id\": \"https:\\/\\/api.cognitive.microsoft.com\\/api\\/v7\\/#WebPages.6\"}}, {\"answerType\": \"WebPages\", \"resultIndex\": 7, \"value\": {\"id\": \"https:\\/\\/api.cognitive.microsoft.com\\/api\\/v7\\/#WebPages.7\"}}, {\"answerType\": \"WebPages\", \"resultIndex\": 8, \"value\": {\"id\": \"https:\\/\\/api.cognitive.microsoft.com\\/api\\/v7\\/#WebPages.8\"}}, {\"answerType\": \"WebPages\", \"resultIndex\": 9, \"value\": {\"id\": \"https:\\/\\/api.cognitive.microsoft.com\\/api\\/v7\\/#WebPages.9\"}}]}}}",
        "relevantHeaders": {
          "BingAPIs-TraceId": "B1059B7CAD874095A5C8BEE6E7C53C2D",
          "BingAPIs-SessionId": "A1021B3BA4654B11A072313617326D17",
          "X-MSEdge-ClientID": "21778155CE9E64341B9B8A99CF316514",
          "BingAPIs-Market": "en-US",
          "X-MSEdge-Ref": "Ref A: B1059B7CAD874095A5C8BEE6E7C53C2D Ref B: BLUEDGE0214 Ref C: 2018-04-09T16:56:55Z"
        },
        "TotalResults": 26000
      },
      "SearchResultWithQuestionPrependedAndCaseInQuotes": {
        "jsonResult": "{\"_type\": \"SearchResponse\", \"queryContext\": {\"originalQuery\": \"which football club has a stand displaying an extract from the nineteenth book of the old testament? \\\"West Bromwich Albion\\\"\"}, \"webPages\": {\"webSearchUrl\": \"https:\\/\\/www.bing.com\\/search?q=which+football+club+has+a+stand+displaying+an+extract+from+the+nineteenth+book+of+the+old+testament%3f+%22West+Bromwich+Albion%22\", \"totalEstimatedMatches\": 11800, \"value\": [{\"id\": \"https:\\/\\/api.cognitive.microsoft.com\\/api\\/v7\\/#WebPages.0\", \"name\": \"Game thread - 22nd February 2018, 9pm GMT : HQEurope\", \"url\": \"https:\\/\\/www.reddit.com\\/r\\/HQEurope\\/comments\\/7zhwbk\\/game_thread_22nd_february_2018_9pm_gmt\\/\", \"isFamilyFriendly\": true, \"displayUrl\": \"https:\\/\\/www.reddit.com\\/r\\/HQEurope\\/comments\\/7zhwbk\\/game_thread_22nd...\", \"snippet\": \"Playing somewhere interesting? Took a piece of the $750 pie? Caught out by a Savage Question? Discuss anything to do with tonight's game...\", \"dateLastCrawled\": \"2018-03-20T20:29:00.0000000Z\", \"language\": \"en\"}, {\"id\": \"https:\\/\\/api.cognitive.microsoft.com\\/api\\/v7\\/#WebPages.1\", \"name\": \"www.assumption.edu\", \"url\": \"http:\\/\\/www.assumption.edu\\/ahc\\/1920s\\/Eugenics\\/Klan.html\", \"about\": [{\"name\": \"Ku Klux Klan\"}], \"isFamilyFriendly\": true, \"displayUrl\": \"www.assumption.edu\\/ahc\\/1920s\\/Eugenics\\/Klan.html\", \"snippet\": \"We would like to show you a description here but the site won’t allow us.\", \"deepLinks\": [{\"name\": \"The KKK in The 1920S\", \"url\": \"http:\\/\\/www1.assumption.edu\\/ahc\\/1920s\\/eugenics\\/Klan.html\"}], \"dateLastCrawled\": \"2018-03-14T20:31:00.0000000Z\", \"language\": \"en\"}, {\"id\": \"https:\\/\\/api.cognitive.microsoft.com\\/api\\/v7\\/#WebPages.2\", \"name\": \"Similar - Books on Google Play\", \"url\": \"https:\\/\\/play.google.com\\/store\\/books\\/collection\\/books_clusters_mrl_rt_BC436E48_AD6ACD28_0E3ED711\", \"isFamilyFriendly\": true, \"displayUrl\": \"https:\\/\\/play.google.com\\/store\\/books\\/collection\\/books_clusters_mrl...\", \"snippet\": \"Among the best known and most quoted books of the Old Testament, the Book of Psalms ... this little book that has ... new challenges—displaying ...\", \"dateLastCrawled\": \"2018-02-16T06:42:00.0000000Z\", \"language\": \"en\"}, {\"id\": \"https:\\/\\/api.cognitive.microsoft.com\\/api\\/v7\\/#WebPages.3\", \"name\": \"Dictionary.com's List of Every Word of the Year ...\", \"url\": \"http:\\/\\/www.dictionary.com\\/e\\/s\\/word-of-the-year-list\\/\", \"about\": [{\"name\": \"Word of the year\"}], \"isFamilyFriendly\": true, \"displayUrl\": \"www.dictionary.com\\/e\\/s\\/word-of-the-year-list\", \"snippet\": \"A list of every Word of the Year selection released by Dictionary.com. Dictionary.com's first Word of the Year was chosen in 2010.\", \"dateLastCrawled\": \"2018-04-05T15:43:00.0000000Z\", \"language\": \"en\"}, {\"id\": \"https:\\/\\/api.cognitive.microsoft.com\\/api\\/v7\\/#WebPages.4\", \"name\": \"Red - Wikipedia\", \"url\": \"https:\\/\\/en.wikipedia.org\\/wiki\\/Red_(color)\", \"about\": [{\"name\": \"Red\"}, {\"name\": \"Red\"}], \"isFamilyFriendly\": true, \"displayUrl\": \"https:\\/\\/en.wikipedia.org\\/wiki\\/Red_(color)\", \"snippet\": \"In the Old Testament of ... In club association football (soccer), red is a commonly ... and the sayings of Mao Zedong were published as a small red book in hundreds ...\", \"dateLastCrawled\": \"2018-04-04T01:34:00.0000000Z\", \"language\": \"en\"}, {\"id\": \"https:\\/\\/api.cognitive.microsoft.com\\/api\\/v7\\/#WebPages.5\", \"name\": \"1902–03 Blackpool F.C. season - WikiVisually\", \"url\": \"https:\\/\\/wikivisually.com\\/wiki\\/1902%E2%80%9303_Blackpool_F.C._season\", \"isFamilyFriendly\": true, \"displayUrl\": \"https:\\/\\/wikivisually.com\\/wiki\\/1902–03_Blackpool_F.C._season\", \"snippet\": \"West Bromwich Albion; ... Jesus was identified with the Sun based on an Old Testament ... the top flight of English football. The club has won 13 League titles ...\", \"dateLastCrawled\": \"2018-02-25T11:20:00.0000000Z\", \"language\": \"en\"}, {\"id\": \"https:\\/\\/api.cognitive.microsoft.com\\/api\\/v7\\/#WebPages.6\", \"name\": \"The State - Online Library of Liberty\", \"url\": \"http:\\/\\/oll.libertyfund.org\\/titles\\/jasay-the-state\", \"isFamilyFriendly\": true, \"displayUrl\": \"oll.libertyfund.org\\/titles\\/jasay-the-state\", \"snippet\": \"Online Library of Liberty. ... While violence and preference may stand ... It is intuitively plausible that in a state of nature where people do not instantly club ...\", \"dateLastCrawled\": \"2018-03-27T09:19:00.0000000Z\", \"language\": \"en\"}, {\"id\": \"https:\\/\\/api.cognitive.microsoft.com\\/api\\/v7\\/#WebPages.7\", \"name\": \"The Project Gutenberg eBook of Memoirs of My Dead Life, by ...\", \"url\": \"http:\\/\\/www.gutenberg.org\\/files\\/7789\\/7789-h\\/7789-h.htm\", \"isFamilyFriendly\": true, \"displayUrl\": \"www.gutenberg.org\\/files\\/7789\\/7789-h\\/7789-h.htm\", \"snippet\": \"The literary compliments he pays me and the interest that my book has excited ... out that in the Old Testament we are told ... the nineteenth century a great ...\", \"dateLastCrawled\": \"2017-12-28T19:33:00.0000000Z\", \"language\": \"en\"}, {\"id\": \"https:\\/\\/api.cognitive.microsoft.com\\/api\\/v7\\/#WebPages.8\", \"name\": \"The Project Gutenberg eBook of The Life of a Regimental ...\", \"url\": \"http:\\/\\/www.gutenberg.org\\/files\\/48274\\/48274-h\\/48274-h.htm\", \"isFamilyFriendly\": true, \"displayUrl\": \"www.gutenberg.org\\/files\\/48274\\/48274-h\\/48274-h.htm\", \"snippet\": \"One has only to glance at a ... in putting this book together, my aim has been not so much to give a ... and during the opening years of the nineteenth, ...\", \"dateLastCrawled\": \"2017-11-19T06:32:00.0000000Z\", \"language\": \"en\"}, {\"id\": \"https:\\/\\/api.cognitive.microsoft.com\\/api\\/v7\\/#WebPages.9\", \"name\": \"SRA76 MARCH 2018 MASONIC MAGAZINE by Stewart Donaldson - issuu\", \"url\": \"https:\\/\\/issuu.com\\/sra76\\/docs\\/03_-_march_2018\", \"isFamilyFriendly\": true, \"displayUrl\": \"https:\\/\\/issuu.com\\/sra76\\/docs\\/03_-_march_2018\", \"snippet\": \"The Installed Master. the Constitution of the Grand Lodge of Scotland, a Masonic degree. There is no such thing as the Degree of Installed Master.\", \"dateLastCrawled\": \"2018-03-26T16:54:00.0000000Z\", \"language\": \"en\"}]}, \"rankingResponse\": {\"mainline\": {\"items\": [{\"answerType\": \"WebPages\", \"resultIndex\": 0, \"value\": {\"id\": \"https:\\/\\/api.cognitive.microsoft.com\\/api\\/v7\\/#WebPages.0\"}}, {\"answerType\": \"WebPages\", \"resultIndex\": 1, \"value\": {\"id\": \"https:\\/\\/api.cognitive.microsoft.com\\/api\\/v7\\/#WebPages.1\"}}, {\"answerType\": \"WebPages\", \"resultIndex\": 2, \"value\": {\"id\": \"https:\\/\\/api.cognitive.microsoft.com\\/api\\/v7\\/#WebPages.2\"}}, {\"answerType\": \"WebPages\", \"resultIndex\": 3, \"value\": {\"id\": \"https:\\/\\/api.cognitive.microsoft.com\\/api\\/v7\\/#WebPages.3\"}}, {\"answerType\": \"WebPages\", \"resultIndex\": 4, \"value\": {\"id\": \"https:\\/\\/api.cognitive.microsoft.com\\/api\\/v7\\/#WebPages.4\"}}, {\"answerType\": \"WebPages\", \"resultIndex\": 5, \"value\": {\"id\": \"https:\\/\\/api.cognitive.microsoft.com\\/api\\/v7\\/#WebPages.5\"}}, {\"answerType\": \"WebPages\", \"resultIndex\": 6, \"value\": {\"id\": \"https:\\/\\/api.cognitive.microsoft.com\\/api\\/v7\\/#WebPages.6\"}}, {\"answerType\": \"WebPages\", \"resultIndex\": 7, \"value\": {\"id\": \"https:\\/\\/api.cognitive.microsoft.com\\/api\\/v7\\/#WebPages.7\"}}, {\"answerType\": \"WebPages\", \"resultIndex\": 8, \"value\": {\"id\": \"https:\\/\\/api.cognitive.microsoft.com\\/api\\/v7\\/#WebPages.8\"}}, {\"answerType\": \"WebPages\", \"resultIndex\": 9, \"value\": {\"id\": \"https:\\/\\/api.cognitive.microsoft.com\\/api\\/v7\\/#WebPages.9\"}}]}}}",
        "relevantHeaders": {
          "BingAPIs-TraceId": "727F21690FB643189EDE2CF69E41E8B2",
          "BingAPIs-SessionId": "49403B1E4C03459CAB9B45FAE79DC313",
          "X-MSEdge-ClientID": "280221BE7ED86EE731AA2A727F776F1A",
          "BingAPIs-Market": "en-US",
          "X-MSEdge-Ref": "Ref A: 727F21690FB643189EDE2CF69E41E8B2 Ref B: BLUEDGE0621 Ref C: 2018-04-09T16:56:55Z"
        },
        "TotalResults": 11800
      },
      "TimesMentionedInQuestionSearchResult": 0,
      "Attributes": null,
      "IsCorrect": true
    }
  }
}