{
  "Id": 971568995215331329,
  "QuestionData": {
    "Number": 0,
    "Question": "The only rock song to exit our solar system in hard-copy form is by what artist?",
    "QuestionForQuery": "the only rock song to exit our solar system in hard-copy form is by what artist?",
    "SearchResult": {
      "jsonResult": "{\"_type\": \"SearchResponse\", \"queryContext\": {\"originalQuery\": \"the only rock song to exit our solar system in hard-copy form is by what artist?\"}, \"webPages\": {\"webSearchUrl\": \"https:\\/\\/www.bing.com\\/search?q=the+only+rock+song+to+exit+our+solar+system+in+hard-copy+form+is+by+what+artist%3f\", \"totalEstimatedMatches\": 281000, \"value\": [{\"id\": \"https:\\/\\/api.cognitive.microsoft.com\\/api\\/v7\\/#WebPages.0\", \"name\": \"Voyager 1 could hurtle past the edge of our solar system ...\", \"url\": \"http:\\/\\/www.dailymail.co.uk\\/sciencetech\\/article-2004173\\/Voyager-1-hurtle-past-edge-solar-interstellar-space-time.html\", \"about\": [{\"name\": \"Voyager 1\"}], \"isFamilyFriendly\": true, \"displayUrl\": \"www.dailymail.co.uk\\/...2004173\\/...solar-interstellar-space-time.html\", \"snippet\": \"It was initially thought that 2014 would see the craft exit our solar system and enter ... a greeting to any form of ... that is not only the best ...\", \"dateLastCrawled\": \"2018-04-01T08:23:00.0000000Z\", \"language\": \"en\"}, {\"id\": \"https:\\/\\/api.cognitive.microsoft.com\\/api\\/v7\\/#WebPages.1\", \"name\": \"Early Earth Tutorial Script - City College of San Francisco\", \"url\": \"https:\\/\\/fog.ccsf.edu\\/~kwiese\\/content\\/Classes\\/EarlyEarthScript.pdf\", \"isFamilyFriendly\": true, \"displayUrl\": \"https:\\/\\/fog.ccsf.edu\\/~kwiese\\/content\\/Classes\\/EarlyEarthScript.pdf\", \"snippet\": \"Early Earth – Tutorial Script ... we now have an understanding of how our universe, solar system, ... *Intro and exit music: ...\", \"dateLastCrawled\": \"2018-03-31T15:11:00.0000000Z\", \"language\": \"en\"}, {\"id\": \"https:\\/\\/api.cognitive.microsoft.com\\/api\\/v7\\/#WebPages.2\", \"name\": \"Edward Tufte forum: Popular Music: The Classic Graphic by ...\", \"url\": \"https:\\/\\/www.edwardtufte.com\\/bboard\\/q-and-a-fetch-msg?msg_id=0002N4\", \"isFamilyFriendly\": true, \"displayUrl\": \"https:\\/\\/www.edwardtufte.com\\/bboard\\/q-and-a-fetch-msg?msg_id=0002N4\", \"snippet\": \"The wonderful visual history of pop\\/rock music by ... We set the music style titles in a different color from the artist ... Planets outside our solar system: ...\", \"dateLastCrawled\": \"2018-04-01T09:09:00.0000000Z\", \"language\": \"en\"}, {\"id\": \"https:\\/\\/api.cognitive.microsoft.com\\/api\\/v7\\/#WebPages.3\", \"name\": \"Solar System Exit Tickets | Solar system, Teacher and ...\", \"url\": \"https:\\/\\/www.pinterest.com\\/pin\\/531917405965505908\\/\", \"isFamilyFriendly\": true, \"displayUrl\": \"https:\\/\\/www.pinterest.com\\/pin\\/531917405965505908\", \"snippet\": \"Solar System Exit Tickets. ... The \\\"Our Solar System\\\" page from NASA.gov gives lots of interesting facts that the students could ... 3 types of rock- a science song ...\", \"dateLastCrawled\": \"2018-01-23T21:19:00.0000000Z\", \"language\": \"en\"}, {\"id\": \"https:\\/\\/api.cognitive.microsoft.com\\/api\\/v7\\/#WebPages.4\", \"name\": \"After 35 Years, Voyager Nears Edge Of Solar System : NPR\", \"url\": \"https:\\/\\/www.npr.org\\/2012\\/09\\/05\\/160609488\\/after-35-years-voyager-nears-edge-of-solar-system\", \"isFamilyFriendly\": true, \"displayUrl\": \"https:\\/\\/www.npr.org\\/2012\\/09\\/05\\/160609488\\/after-35-years-voyager...\", \"snippet\": \"After 35 Years, Voyager Nears Edge Of Solar System One of the twin space ... is on the verge of leaving our solar system. ... 1 to exit the bubble of ...\", \"dateLastCrawled\": \"2018-03-27T00:21:00.0000000Z\", \"language\": \"en\"}, {\"id\": \"https:\\/\\/api.cognitive.microsoft.com\\/api\\/v7\\/#WebPages.5\", \"name\": \"The Ingredients For Life Have Been Detected In A Star System\", \"url\": \"http:\\/\\/uproxx.com\\/life\\/ingredients-for-life-detected-in-space\\/\", \"isFamilyFriendly\": true, \"displayUrl\": \"uproxx.com\\/life\\/ingredients-for-life-detected-in-space\", \"snippet\": \"Not only have researchers recently found water ... (meaning the type of young star from which our own Solar System ... \\\"The Ingredients For Life Have Been ...\", \"dateLastCrawled\": \"2018-03-21T18:07:00.0000000Z\", \"language\": \"en\"}, {\"id\": \"https:\\/\\/api.cognitive.microsoft.com\\/api\\/v7\\/#WebPages.6\", \"name\": \"Otherworlds: Visions of our Solar System | Things to do in ...\", \"url\": \"https:\\/\\/www.timeout.com\\/london\\/things-to-do\\/otherworlds-visions-of-our-solar-system\", \"isFamilyFriendly\": true, \"displayUrl\": \"https:\\/\\/www.timeout.com\\/...\\/otherworlds-visions-of-our-solar-system\", \"snippet\": \"Otherworlds: Visions of our Solar System. ... you will find as you exit through the well ... art and music to take you on a journey through our humble solar ...\", \"dateLastCrawled\": \"2018-04-03T03:01:00.0000000Z\", \"language\": \"en\"}, {\"id\": \"https:\\/\\/api.cognitive.microsoft.com\\/api\\/v7\\/#WebPages.7\", \"name\": \"The 15 New York Gallery Shows You Need to See This ... - Artsy\", \"url\": \"https:\\/\\/www.artsy.net\\/article\\/artsy-editorial-the-15-new-york-gallery-shows-you-need-to-see-this-september\", \"isFamilyFriendly\": true, \"displayUrl\": \"https:\\/\\/www.artsy.net\\/article\\/artsy-editorial-the-15-new-york...\", \"snippet\": \"The edges of each form are so smooth that they ... time on each planet in our solar system. ... footsteps of emergency floor plans—only to reach the exit and ...\", \"dateLastCrawled\": \"2017-12-15T12:36:00.0000000Z\", \"language\": \"en\"}, {\"id\": \"https:\\/\\/api.cognitive.microsoft.com\\/api\\/v7\\/#WebPages.8\", \"name\": \"Exo-planet with 'extraordinarily eccentric orbit' found ...\", \"url\": \"http:\\/\\/www.dailymail.co.uk\\/sciencetech\\/article-5091157\\/The-exo-planet-extraordinarily-eccentric-orbit.html\", \"isFamilyFriendly\": true, \"displayUrl\": \"www.dailymail.co.uk\\/...\\/The-exo...extraordinarily-eccentric-orbit.html\", \"snippet\": \"Astronomers discover doomed exo-planet with an 'extraordinarily eccentric orbit' ... us understand more about how planetary systems form and ... our Solar system.\", \"dateLastCrawled\": \"2018-04-01T08:31:00.0000000Z\", \"language\": \"en\"}, {\"id\": \"https:\\/\\/api.cognitive.microsoft.com\\/api\\/v7\\/#WebPages.9\", \"name\": \"Which | Define Which at Dictionary.com\", \"url\": \"http:\\/\\/www.dictionary.com\\/browse\\/which\", \"isFamilyFriendly\": true, \"displayUrl\": \"www.dictionary.com\\/browse\\/which\", \"snippet\": \"Try Our Apps definitions. definitions; ... which we had seen only from a distance, ... (archaic) the which, a longer form of which, ...\", \"dateLastCrawled\": \"2018-04-02T10:06:00.0000000Z\", \"language\": \"en\"}]}, \"rankingResponse\": {\"mainline\": {\"items\": [{\"answerType\": \"WebPages\", \"resultIndex\": 0, \"value\": {\"id\": \"https:\\/\\/api.cognitive.microsoft.com\\/api\\/v7\\/#WebPages.0\"}}, {\"answerType\": \"WebPages\", \"resultIndex\": 1, \"value\": {\"id\": \"https:\\/\\/api.cognitive.microsoft.com\\/api\\/v7\\/#WebPages.1\"}}, {\"answerType\": \"WebPages\", \"resultIndex\": 2, \"value\": {\"id\": \"https:\\/\\/api.cognitive.microsoft.com\\/api\\/v7\\/#WebPages.2\"}}, {\"answerType\": \"WebPages\", \"resultIndex\": 3, \"value\": {\"id\": \"https:\\/\\/api.cognitive.microsoft.com\\/api\\/v7\\/#WebPages.3\"}}, {\"answerType\": \"WebPages\", \"resultIndex\": 4, \"value\": {\"id\": \"https:\\/\\/api.cognitive.microsoft.com\\/api\\/v7\\/#WebPages.4\"}}, {\"answerType\": \"WebPages\", \"resultIndex\": 5, \"value\": {\"id\": \"https:\\/\\/api.cognitive.microsoft.com\\/api\\/v7\\/#WebPages.5\"}}, {\"answerType\": \"WebPages\", \"resultIndex\": 6, \"value\": {\"id\": \"https:\\/\\/api.cognitive.microsoft.com\\/api\\/v7\\/#WebPages.6\"}}, {\"answerType\": \"WebPages\", \"resultIndex\": 7, \"value\": {\"id\": \"https:\\/\\/api.cognitive.microsoft.com\\/api\\/v7\\/#WebPages.7\"}}, {\"answerType\": \"WebPages\", \"resultIndex\": 8, \"value\": {\"id\": \"https:\\/\\/api.cognitive.microsoft.com\\/api\\/v7\\/#WebPages.8\"}}, {\"answerType\": \"WebPages\", \"resultIndex\": 9, \"value\": {\"id\": \"https:\\/\\/api.cognitive.microsoft.com\\/api\\/v7\\/#WebPages.9\"}}]}}}",
      "relevantHeaders": {
        "BingAPIs-TraceId": "A375609206F04A6C85EA86466A574E7F",
        "BingAPIs-SessionId": "E79441B9716B402BA01588DDF6DB246B",
        "X-MSEdge-ClientID": "30C012E3AEFB6C153F23192FAF546D9C",
        "BingAPIs-Market": "en-US",
        "X-MSEdge-Ref": "Ref A: A375609206F04A6C85EA86466A574E7F Ref B: BLUEDGE0708 Ref C: 2018-04-09T16:54:46Z"
      },
      "TotalResults": 281000
    },
    "SearchResultWithModifiedQuery": {
      "jsonResult": null,
      "relevantHeaders": null,
      "TotalResults": 0
    },
    "Attributes": []
  },
  "CasesData": {
    "1": {
      "Case": "The Beatles",
      "SearchResultWithQuestionPrepended": {
        "jsonResult": "{\"_type\": \"SearchResponse\", \"queryContext\": {\"originalQuery\": \"the only rock song to exit our solar system in hard-copy form is by what artist? The Beatles\"}, \"webPages\": {\"webSearchUrl\": \"https:\\/\\/www.bing.com\\/search?q=the+only+rock+song+to+exit+our+solar+system+in+hard-copy+form+is+by+what+artist%3f+The+Beatles\", \"totalEstimatedMatches\": 178000, \"value\": [{\"id\": \"https:\\/\\/api.cognitive.microsoft.com\\/api\\/v7\\/#WebPages.0\", \"name\": \"Voyager 1 could hurtle past the edge of our solar system ...\", \"url\": \"http:\\/\\/www.dailymail.co.uk\\/sciencetech\\/article-2004173\\/Voyager-1-hurtle-past-edge-solar-interstellar-space-time.html\", \"about\": [{\"name\": \"Voyager 1\"}], \"isFamilyFriendly\": true, \"displayUrl\": \"www.dailymail.co.uk\\/...2004173\\/...solar-interstellar-space-time.html\", \"snippet\": \"It was initially thought that 2014 would see the craft exit our solar system and ... with The Beatles' hits for her role ... is not only the best ...\", \"dateLastCrawled\": \"2018-04-01T08:23:00.0000000Z\", \"language\": \"en\"}, {\"id\": \"https:\\/\\/api.cognitive.microsoft.com\\/api\\/v7\\/#WebPages.1\", \"name\": \"Edward Tufte forum: Popular Music: The Classic Graphic by ...\", \"url\": \"https:\\/\\/www.edwardtufte.com\\/bboard\\/q-and-a-fetch-msg?msg_id=0002N4\", \"isFamilyFriendly\": true, \"displayUrl\": \"https:\\/\\/www.edwardtufte.com\\/bboard\\/q-and-a-fetch-msg?msg_id=0002N4\", \"snippet\": \"The wonderful visual history of pop\\/rock music by ... We set the music style titles in a different color from the artist ... Planets outside our solar system: ...\", \"dateLastCrawled\": \"2018-04-01T09:09:00.0000000Z\", \"language\": \"en\"}, {\"id\": \"https:\\/\\/api.cognitive.microsoft.com\\/api\\/v7\\/#WebPages.2\", \"name\": \"What Is on Voyager’s Golden Record? | Science | Smithsonian\", \"url\": \"https:\\/\\/www.smithsonianmag.com\\/science-nature\\/what-is-on-voyagers-golden-record-73063839\\/\", \"isFamilyFriendly\": true, \"displayUrl\": \"https:\\/\\/www.smithsonianmag.com\\/science-nature\\/what-is-on-voyagers...\", \"snippet\": \"Produce a phonograph record containing the sounds and images of humankind and fling it out into the solar system. ... time and location of our ... rock music was ...\", \"dateLastCrawled\": \"2018-04-04T20:58:00.0000000Z\", \"language\": \"en\"}, {\"id\": \"https:\\/\\/api.cognitive.microsoft.com\\/api\\/v7\\/#WebPages.3\", \"name\": \"Did a supernova trigger the birth of the solar system ...\", \"url\": \"http:\\/\\/www.dailymail.co.uk\\/sciencetech\\/article-3204590\\/Did-supernova-trigger-birth-solar-Shockwaves-triggered-formation-rotation-planets.html\", \"isFamilyFriendly\": true, \"displayUrl\": \"www.dailymail.co.uk\\/sciencetech\\/article-3204590\\/Did-supernova...\", \"snippet\": \"... how a supernova explosion gave our solar system ... the early solar system to spin, allowing the planets to form instead of ... is not only the best ...\", \"dateLastCrawled\": \"2018-04-01T00:47:00.0000000Z\", \"language\": \"en\"}, {\"id\": \"https:\\/\\/api.cognitive.microsoft.com\\/api\\/v7\\/#WebPages.4\", \"name\": \"The Latest On AXS\", \"url\": \"http:\\/\\/m.axs.com\\/thelatestonaxs\", \"isFamilyFriendly\": true, \"displayUrl\": \"m.axs.com\\/thelatestonaxs\", \"snippet\": \"By continuing to use our website you ... New Weeklings single bounces with Beatles love and a nod to progressive rock. ... Artist Bernard Rangel exhibits at the ...\", \"dateLastCrawled\": \"2018-03-08T04:12:00.0000000Z\", \"language\": \"en\"}, {\"id\": \"https:\\/\\/api.cognitive.microsoft.com\\/api\\/v7\\/#WebPages.5\", \"name\": \"Hallo spaceboy | The Monthly\", \"url\": \"https:\\/\\/www.themonthly.com.au\\/issue\\/2015\\/august\\/1438351200\\/anwen-crawford\\/hallo-spaceboy\", \"isFamilyFriendly\": true, \"displayUrl\": \"https:\\/\\/www.themonthly.com.au\\/issue\\/2015\\/august\\/1438351200\\/anwen...\", \"snippet\": \"... outer limits of our solar system, ... pop music is a familiar cultural form. Only the stuffiest ... Rex to glam-rock superstardom. Bowie is the better artist, ...\", \"dateLastCrawled\": \"2018-03-25T02:47:00.0000000Z\", \"language\": \"en\"}, {\"id\": \"https:\\/\\/api.cognitive.microsoft.com\\/api\\/v7\\/#WebPages.6\", \"name\": \"Myspace - Official Site\", \"url\": \"https:\\/\\/myspace.com\\/\", \"about\": [{\"name\": \"Myspace\"}, {\"name\": \"Myspace\"}], \"isFamilyFriendly\": true, \"displayUrl\": \"https:\\/\\/myspace.com\", \"snippet\": \"Movie buffs aren’t the only ones in for a treat at the ... It’s the story of a humble rock ... Welcome to Myspace. Just start typing to find music. Queue;\", \"dateLastCrawled\": \"2018-04-05T11:32:00.0000000Z\", \"language\": \"en\"}, {\"id\": \"https:\\/\\/api.cognitive.microsoft.com\\/api\\/v7\\/#WebPages.7\", \"name\": \"Mary Swift (maryswiftwriter) on Pinterest\", \"url\": \"https:\\/\\/www.pinterest.com\\/maryswiftwriter\\/\", \"isFamilyFriendly\": true, \"displayUrl\": \"https:\\/\\/www.pinterest.com\\/maryswiftwriter\", \"snippet\": \"See what Mary Swift (maryswiftwriter) ... A compass and the solar system, ... the 13 coolest alter-egos in music. From The Beatles to Lana Del Rey and Arctic Monkeys.\", \"dateLastCrawled\": \"2018-04-04T19:12:00.0000000Z\", \"language\": \"en\"}, {\"id\": \"https:\\/\\/api.cognitive.microsoft.com\\/api\\/v7\\/#WebPages.8\", \"name\": \"HMS X-1 | Submarines | Pinterest | Ships\", \"url\": \"https:\\/\\/www.pinterest.com\\/pin\\/532832199637557452\\/\", \"isFamilyFriendly\": true, \"displayUrl\": \"https:\\/\\/www.pinterest.com\\/pin\\/532832199637557452\", \"snippet\": \"Beatles Lyrics Songs By The Beatles Beatles Poster Beatles Quotes Music Lyrics Beatles Art Submarines Yellow ... to explore our Solar System's ... submarines exit.\", \"dateLastCrawled\": \"2018-03-23T19:31:00.0000000Z\", \"language\": \"en\"}, {\"id\": \"https:\\/\\/api.cognitive.microsoft.com\\/api\\/v7\\/#WebPages.9\", \"name\": \"2001: A Space Odyssey (1968) - Trivia - IMDb\", \"url\": \"http:\\/\\/www.imdb.com\\/title\\/tt0062622\\/trivia\", \"about\": [{\"name\": \"2001: A Space Odyssey\"}, {\"name\": \"2001: A Space Odyssey\"}], \"isFamilyFriendly\": true, \"displayUrl\": \"www.imdb.com\\/title\\/tt0062622\\/trivia\", \"snippet\": \"2001: A Space Odyssey (1968) ... \\\"How the Solar System was Won\\\", ... Intermission, and Exit Music were not used, ...\", \"dateLastCrawled\": \"2018-03-23T08:20:00.0000000Z\", \"language\": \"en\"}]}, \"rankingResponse\": {\"mainline\": {\"items\": [{\"answerType\": \"WebPages\", \"resultIndex\": 0, \"value\": {\"id\": \"https:\\/\\/api.cognitive.microsoft.com\\/api\\/v7\\/#WebPages.0\"}}, {\"answerType\": \"WebPages\", \"resultIndex\": 1, \"value\": {\"id\": \"https:\\/\\/api.cognitive.microsoft.com\\/api\\/v7\\/#WebPages.1\"}}, {\"answerType\": \"WebPages\", \"resultIndex\": 2, \"value\": {\"id\": \"https:\\/\\/api.cognitive.microsoft.com\\/api\\/v7\\/#WebPages.2\"}}, {\"answerType\": \"WebPages\", \"resultIndex\": 3, \"value\": {\"id\": \"https:\\/\\/api.cognitive.microsoft.com\\/api\\/v7\\/#WebPages.3\"}}, {\"answerType\": \"WebPages\", \"resultIndex\": 4, \"value\": {\"id\": \"https:\\/\\/api.cognitive.microsoft.com\\/api\\/v7\\/#WebPages.4\"}}, {\"answerType\": \"WebPages\", \"resultIndex\": 5, \"value\": {\"id\": \"https:\\/\\/api.cognitive.microsoft.com\\/api\\/v7\\/#WebPages.5\"}}, {\"answerType\": \"WebPages\", \"resultIndex\": 6, \"value\": {\"id\": \"https:\\/\\/api.cognitive.microsoft.com\\/api\\/v7\\/#WebPages.6\"}}, {\"answerType\": \"WebPages\", \"resultIndex\": 7, \"value\": {\"id\": \"https:\\/\\/api.cognitive.microsoft.com\\/api\\/v7\\/#WebPages.7\"}}, {\"answerType\": \"WebPages\", \"resultIndex\": 8, \"value\": {\"id\": \"https:\\/\\/api.cognitive.microsoft.com\\/api\\/v7\\/#WebPages.8\"}}, {\"answerType\": \"WebPages\", \"resultIndex\": 9, \"value\": {\"id\": \"https:\\/\\/api.cognitive.microsoft.com\\/api\\/v7\\/#WebPages.9\"}}]}}}",
        "relevantHeaders": {
          "BingAPIs-TraceId": "A97B1EF0BC994074B893856E04207D66",
          "BingAPIs-SessionId": "AA31F091869E4103A5F02789B037DA86",
          "X-MSEdge-ClientID": "13A44FE1BBA662B92BB3442DBA096383",
          "BingAPIs-Market": "en-US",
          "X-MSEdge-Ref": "Ref A: A97B1EF0BC994074B893856E04207D66 Ref B: BLUEDGE0414 Ref C: 2018-04-09T16:54:46Z"
        },
        "TotalResults": 178000
      },
      "SearchResultWithQuestionPrependedAndCaseInQuotes": {
        "jsonResult": "{\"_type\": \"SearchResponse\", \"queryContext\": {\"originalQuery\": \"the only rock song to exit our solar system in hard-copy form is by what artist? \\\"The Beatles\\\"\"}, \"webPages\": {\"webSearchUrl\": \"https:\\/\\/www.bing.com\\/search?q=the+only+rock+song+to+exit+our+solar+system+in+hard-copy+form+is+by+what+artist%3f+%22The+Beatles%22\", \"totalEstimatedMatches\": 85600, \"value\": [{\"id\": \"https:\\/\\/api.cognitive.microsoft.com\\/api\\/v7\\/#WebPages.0\", \"name\": \"Voyager 1 could hurtle past the edge of our solar system ...\", \"url\": \"http:\\/\\/www.dailymail.co.uk\\/sciencetech\\/article-2004173\\/Voyager-1-hurtle-past-edge-solar-interstellar-space-time.html\", \"about\": [{\"name\": \"Voyager 1\"}], \"isFamilyFriendly\": true, \"displayUrl\": \"www.dailymail.co.uk\\/...2004173\\/...solar-interstellar-space-time.html\", \"snippet\": \"It was initially thought that 2014 would see the craft exit our solar system and enter ... to any form of life, should that ... with The Beatles' hits for her role in ...\", \"dateLastCrawled\": \"2018-04-01T08:23:00.0000000Z\", \"language\": \"en\"}, {\"id\": \"https:\\/\\/api.cognitive.microsoft.com\\/api\\/v7\\/#WebPages.1\", \"name\": \"Edward Tufte forum: Popular Music: The Classic Graphic by ...\", \"url\": \"https:\\/\\/www.edwardtufte.com\\/bboard\\/q-and-a-fetch-msg?msg_id=0002N4\", \"isFamilyFriendly\": true, \"displayUrl\": \"https:\\/\\/www.edwardtufte.com\\/bboard\\/q-and-a-fetch-msg?msg_id=0002N4\", \"snippet\": \"The wonderful visual history of pop\\/rock music by ... We set the music style titles in a different color from the artist ... Planets outside our solar system: ...\", \"dateLastCrawled\": \"2018-04-01T09:09:00.0000000Z\", \"language\": \"en\"}, {\"id\": \"https:\\/\\/api.cognitive.microsoft.com\\/api\\/v7\\/#WebPages.2\", \"name\": \"Did a supernova trigger the birth of the solar system ...\", \"url\": \"http:\\/\\/www.dailymail.co.uk\\/sciencetech\\/article-3204590\\/Did-supernova-trigger-birth-solar-Shockwaves-triggered-formation-rotation-planets.html\", \"isFamilyFriendly\": true, \"displayUrl\": \"www.dailymail.co.uk\\/sciencetech\\/article-3204590\\/Did-supernova...\", \"snippet\": \"A shock wave from a supernova explosion crashed into a cloud of gas giving birth to our sun. Radioisotopes created in this explosion also caused the early solar system to spin, allowing the planets to form instead of collapsing into the sun.\", \"dateLastCrawled\": \"2018-04-01T00:47:00.0000000Z\", \"language\": \"en\"}, {\"id\": \"https:\\/\\/api.cognitive.microsoft.com\\/api\\/v7\\/#WebPages.3\", \"name\": \"What Is on Voyager’s Golden Record? | Science | Smithsonian\", \"url\": \"https:\\/\\/www.smithsonianmag.com\\/science-nature\\/what-is-on-voyagers-golden-record-73063839\\/\", \"isFamilyFriendly\": true, \"displayUrl\": \"https:\\/\\/www.smithsonianmag.com\\/science-nature\\/what-is-on-voyagers...\", \"snippet\": \"Produce a phonograph record containing the sounds and images of humankind and fling it out into the solar system. ... time and location of our ... rock music was ...\", \"dateLastCrawled\": \"2018-04-04T20:58:00.0000000Z\", \"language\": \"en\"}, {\"id\": \"https:\\/\\/api.cognitive.microsoft.com\\/api\\/v7\\/#WebPages.4\", \"name\": \"Hallo spaceboy | The Monthly\", \"url\": \"https:\\/\\/www.themonthly.com.au\\/issue\\/2015\\/august\\/1438351200\\/anwen-crawford\\/hallo-spaceboy\", \"isFamilyFriendly\": true, \"displayUrl\": \"https:\\/\\/www.themonthly.com.au\\/issue\\/2015\\/august\\/1438351200\\/anwen...\", \"snippet\": \"... outer limits of our solar system, ... pop music is a familiar cultural form. Only the stuffiest ... Rex to glam-rock superstardom. Bowie is the better artist, ...\", \"dateLastCrawled\": \"2018-03-25T02:47:00.0000000Z\", \"language\": \"en\"}, {\"id\": \"https:\\/\\/api.cognitive.microsoft.com\\/api\\/v7\\/#WebPages.5\", \"name\": \"43 best Moons images on Pinterest | Solar system, Outer ...\", \"url\": \"https:\\/\\/www.pinterest.com\\/groovylabinabox\\/moons\\/\", \"isFamilyFriendly\": true, \"displayUrl\": \"https:\\/\\/www.pinterest.com\\/groovylabinabox\\/moons\", \"snippet\": \"My favorite song by my favorite artist:) ... of our solar system.there may be only nine ... to all the moons in our solar system and Voila! saddly ...\", \"dateLastCrawled\": \"2018-03-28T21:39:00.0000000Z\", \"language\": \"en\"}, {\"id\": \"https:\\/\\/api.cognitive.microsoft.com\\/api\\/v7\\/#WebPages.6\", \"name\": \"287 best My Music- Classic Rock images on Pinterest ...\", \"url\": \"https:\\/\\/www.pinterest.com\\/barbaradreyfus\\/my-music-classic-rock\\/\", \"isFamilyFriendly\": true, \"displayUrl\": \"https:\\/\\/www.pinterest.com\\/barbaradreyfus\\/my-music-classic-rock\", \"snippet\": \"Explore Barbara Dreyfus's board \\\"My Music- Classic Rock\\\" on ... Track Cinema Theater Star Solar System Music ... Matter What Music Therapy The Beatles Rock Bands ...\", \"dateLastCrawled\": \"2018-03-08T01:44:00.0000000Z\", \"language\": \"en\"}, {\"id\": \"https:\\/\\/api.cognitive.microsoft.com\\/api\\/v7\\/#WebPages.7\", \"name\": \"Community Audio : Free Audio : Download & Streaming ...\", \"url\": \"https:\\/\\/archive.org\\/details\\/opensource_audio?and%5B%5D=mediatype%3A%22audio%22&and%5B%5D=subject%3A%22rock%22&sort=&page=2\", \"isFamilyFriendly\": true, \"displayUrl\": \"https:\\/\\/archive.org\\/details\\/opensource_audio?and[]=mediatype:\\\"audio...\", \"snippet\": \"NASA Images Solar System Collection Ames Research Center. ... Music Artist: Robert Kunin Title: ... Remco Takken was more on the Beatles' side, ...\", \"dateLastCrawled\": \"2018-03-23T19:39:00.0000000Z\", \"language\": \"en\"}, {\"id\": \"https:\\/\\/api.cognitive.microsoft.com\\/api\\/v7\\/#WebPages.8\", \"name\": \"The Beach Boys - RiNet\", \"url\": \"http:\\/\\/starling.rinet.ru\\/music\\/beachc.htm\", \"isFamilyFriendly\": true, \"displayUrl\": \"starling.rinet.ru\\/music\\/beachc.htm\", \"snippet\": \"... songs about the solar system and ... version of the Beatles,' the Beach Boys were indeed a ... rock into an art form. The Beatles' Sgt. Pepper's ...\", \"dateLastCrawled\": \"2018-03-24T04:22:00.0000000Z\", \"language\": \"en\"}, {\"id\": \"https:\\/\\/api.cognitive.microsoft.com\\/api\\/v7\\/#WebPages.9\", \"name\": \"WHRW - DJ Blog\", \"url\": \"http:\\/\\/www.whrwfm.org\\/shows\\/blog\\/2011\\/sep\\/\", \"isFamilyFriendly\": true, \"displayUrl\": \"www.whrwfm.org\\/shows\\/blog\\/2011\\/sep\", \"snippet\": \"Artist – Song. Mogwai – Like Herod ... our lady of parc extension and her munificent sorrows ... – The Beatles Bargain – The Who Helpless – Crosby, Stills ...\", \"dateLastCrawled\": \"2018-03-02T21:16:00.0000000Z\", \"language\": \"en\"}]}, \"rankingResponse\": {\"mainline\": {\"items\": [{\"answerType\": \"WebPages\", \"resultIndex\": 0, \"value\": {\"id\": \"https:\\/\\/api.cognitive.microsoft.com\\/api\\/v7\\/#WebPages.0\"}}, {\"answerType\": \"WebPages\", \"resultIndex\": 1, \"value\": {\"id\": \"https:\\/\\/api.cognitive.microsoft.com\\/api\\/v7\\/#WebPages.1\"}}, {\"answerType\": \"WebPages\", \"resultIndex\": 2, \"value\": {\"id\": \"https:\\/\\/api.cognitive.microsoft.com\\/api\\/v7\\/#WebPages.2\"}}, {\"answerType\": \"WebPages\", \"resultIndex\": 3, \"value\": {\"id\": \"https:\\/\\/api.cognitive.microsoft.com\\/api\\/v7\\/#WebPages.3\"}}, {\"answerType\": \"WebPages\", \"resultIndex\": 4, \"value\": {\"id\": \"https:\\/\\/api.cognitive.microsoft.com\\/api\\/v7\\/#WebPages.4\"}}, {\"answerType\": \"WebPages\", \"resultIndex\": 5, \"value\": {\"id\": \"https:\\/\\/api.cognitive.microsoft.com\\/api\\/v7\\/#WebPages.5\"}}, {\"answerType\": \"WebPages\", \"resultIndex\": 6, \"value\": {\"id\": \"https:\\/\\/api.cognitive.microsoft.com\\/api\\/v7\\/#WebPages.6\"}}, {\"answerType\": \"WebPages\", \"resultIndex\": 7, \"value\": {\"id\": \"https:\\/\\/api.cognitive.microsoft.com\\/api\\/v7\\/#WebPages.7\"}}, {\"answerType\": \"WebPages\", \"resultIndex\": 8, \"value\": {\"id\": \"https:\\/\\/api.cognitive.microsoft.com\\/api\\/v7\\/#WebPages.8\"}}, {\"answerType\": \"WebPages\", \"resultIndex\": 9, \"value\": {\"id\": \"https:\\/\\/api.cognitive.microsoft.com\\/api\\/v7\\/#WebPages.9\"}}]}}}",
        "relevantHeaders": {
          "BingAPIs-TraceId": "CDAC53CDD6634AE4868B8B0AD738C48C",
          "BingAPIs-SessionId": "442F19080A8847DAA13414992151A705",
          "X-MSEdge-ClientID": "125D6BAFCC1B6C3F25096063CDB46D11",
          "BingAPIs-Market": "en-US",
          "X-MSEdge-Ref": "Ref A: CDAC53CDD6634AE4868B8B0AD738C48C Ref B: BLUEDGE0418 Ref C: 2018-04-09T16:54:46Z"
        },
        "TotalResults": 85600
      },
      "TimesMentionedInQuestionSearchResult": 0,
      "Attributes": null,
      "IsCorrect": false
    },
    "2": {
      "Case": "Chuck Berry",
      "SearchResultWithQuestionPrepended": {
        "jsonResult": "{\"_type\": \"SearchResponse\", \"queryContext\": {\"originalQuery\": \"the only rock song to exit our solar system in hard-copy form is by what artist? Chuck Berry\"}, \"webPages\": {\"webSearchUrl\": \"https:\\/\\/www.bing.com\\/search?q=the+only+rock+song+to+exit+our+solar+system+in+hard-copy+form+is+by+what+artist%3f+Chuck+Berry\", \"totalEstimatedMatches\": 239000, \"value\": [{\"id\": \"https:\\/\\/api.cognitive.microsoft.com\\/api\\/v7\\/#WebPages.0\", \"name\": \"What Is on Voyager’s Golden Record? | Science | Smithsonian\", \"url\": \"https:\\/\\/www.smithsonianmag.com\\/science-nature\\/what-is-on-voyagers-golden-record-73063839\\/\", \"isFamilyFriendly\": true, \"displayUrl\": \"https:\\/\\/www.smithsonianmag.com\\/science-nature\\/what-is-on-voyagers...\", \"snippet\": \"Produce a phonograph record containing the sounds and images of humankind and fling it out into the solar system. ... Chuck Berry’s ... arguing that rock music was ...\", \"dateLastCrawled\": \"2018-04-04T20:58:00.0000000Z\", \"language\": \"en\"}, {\"id\": \"https:\\/\\/api.cognitive.microsoft.com\\/api\\/v7\\/#WebPages.1\", \"name\": \"1972 | Nostalgia Central\", \"url\": \"http:\\/\\/nostalgiacentral.com\\/decades\\/1970s\\/1972year\\/\", \"isFamilyFriendly\": true, \"displayUrl\": \"nostalgiacentral.com\\/decades\\/1970s\\/1972year\", \"snippet\": \"... Pioneer 10 will eventually become the first spacecraft to exit our solar system. 03 ... Rock ‘n’ Roll Show features Chuck Berry, ... in 1972 than any artist ...\", \"dateLastCrawled\": \"2018-03-27T23:56:00.0000000Z\", \"language\": \"en\"}, {\"id\": \"https:\\/\\/api.cognitive.microsoft.com\\/api\\/v7\\/#WebPages.2\", \"name\": \"Reagan Academic Team Questions-2016 (excluding math ...\", \"url\": \"https:\\/\\/quizlet.com\\/164858739\\/reagan-academic-team-questions-2016-excluding-math-flash-cards\\/\", \"isFamilyFriendly\": true, \"displayUrl\": \"https:\\/\\/quizlet.com\\/164858739\\/reagan-academic-team-questions-2016...\", \"snippet\": \"Reagan Academic Team Questions-2016 (excluding math) ... and Chuck Berry; Elvis sang this style of music. ... bodies and the sun being the center of the solar system, ...\", \"dateLastCrawled\": \"2018-04-02T02:39:00.0000000Z\", \"language\": \"en\"}, {\"id\": \"https:\\/\\/api.cognitive.microsoft.com\\/api\\/v7\\/#WebPages.3\", \"name\": \"Peliculotas\", \"url\": \"http:\\/\\/www.peliculotas.com\\/\", \"isFamilyFriendly\": true, \"displayUrl\": \"www.peliculotas.com\", \"snippet\": \"We would like to show you a description here but the site won’t allow us.\", \"dateLastCrawled\": \"2018-04-03T03:27:00.0000000Z\", \"language\": \"es\"}, {\"id\": \"https:\\/\\/api.cognitive.microsoft.com\\/api\\/v7\\/#WebPages.4\", \"name\": \"Spirals of dust around stars may be disguising Earth 2.0 ...\", \"url\": \"http:\\/\\/www.dailymail.co.uk\\/sciencetech\\/article-3297486\\/Spirals-dust-stars-hiding-Earth-2-0-Stellar-material-disguising-massive-planets-claims-study.html\", \"isFamilyFriendly\": true, \"displayUrl\": \"www.dailymail.co.uk\\/sciencetech\\/article-3297486\\/Spirals-dust-stars...\", \"snippet\": \"... the largest planet in our solar system. ... Artist Chuck Connelly paints ... Kendrick Lamar accused of copying British-Liberian artist's work in music video for ...\", \"dateLastCrawled\": \"2018-02-16T12:20:00.0000000Z\", \"language\": \"en\"}, {\"id\": \"https:\\/\\/api.cognitive.microsoft.com\\/api\\/v7\\/#WebPages.5\", \"name\": \"70 best Music images on Pinterest | Lyrics, Music lyrics ...\", \"url\": \"https:\\/\\/www.pinterest.com\\/beesprivvyacc\\/music\\/\", \"isFamilyFriendly\": true, \"displayUrl\": \"https:\\/\\/www.pinterest.com\\/beesprivvyacc\\/music\", \"snippet\": \"... we used to have really good rock music before you ... Chuck Berry & Nirvana ... Smile Google Search Polar Region Fountain Posts Exploring Sun Solar System ...\", \"dateLastCrawled\": \"2018-04-04T22:11:00.0000000Z\", \"language\": \"en\"}, {\"id\": \"https:\\/\\/api.cognitive.microsoft.com\\/api\\/v7\\/#WebPages.6\", \"name\": \"The Farthest (2017) Movie Script | SS\", \"url\": \"https:\\/\\/www.springfieldspringfield.co.uk\\/movie_script.php?movie=the-farthest\", \"isFamilyFriendly\": true, \"displayUrl\": \"https:\\/\\/www.springfieldspringfield.co.uk\\/movie_script.php?movie=...\", \"snippet\": \"The Farthest (2017) Movie Script. Read the The Farthest full movie ... that you can only explore the solar system for the first time ... Chuck Berry's Johnny B ...\", \"dateLastCrawled\": \"2018-03-18T08:24:00.0000000Z\", \"language\": \"en\"}, {\"id\": \"https:\\/\\/api.cognitive.microsoft.com\\/api\\/v7\\/#WebPages.7\", \"name\": \"Dictionary.com's List of Every Word of the Year ...\", \"url\": \"http:\\/\\/www.dictionary.com\\/e\\/s\\/word-of-the-year-list\\/\", \"about\": [{\"name\": \"Word of the year\"}], \"isFamilyFriendly\": true, \"displayUrl\": \"www.dictionary.com\\/e\\/s\\/word-of-the-year-list\", \"snippet\": \"A list of every Word of the Year selection released by Dictionary.com. Dictionary.com's first Word of the Year ... Only time will tell if the ... Our choice for Word ...\", \"dateLastCrawled\": \"2018-04-05T15:43:00.0000000Z\", \"language\": \"en\"}, {\"id\": \"https:\\/\\/api.cognitive.microsoft.com\\/api\\/v7\\/#WebPages.8\", \"name\": \"Buffalo State’s Whitworth Ferguson Planetarium present’s ...\", \"url\": \"https:\\/\\/www.buffalorising.com\\/2017\\/04\\/buffalo-states-whitworth-ferguson-planetarium-presents-planets-beyond-our-solar-system\\/\", \"isFamilyFriendly\": true, \"displayUrl\": \"https:\\/\\/www.buffalorising.com\\/2017\\/04\\/buffalo-states-whitworth...\", \"snippet\": \"Buffalo State’s Whitworth Ferguson Planetarium present’s “Planets Beyond Our Solar System ... featuring the program “Planets Beyond Our Solar System”.\", \"dateLastCrawled\": \"2018-03-15T00:55:00.0000000Z\", \"language\": \"en\"}, {\"id\": \"https:\\/\\/api.cognitive.microsoft.com\\/api\\/v7\\/#WebPages.9\", \"name\": \"Angelica Saario (angelicasaario) on Pinterest\", \"url\": \"https:\\/\\/www.pinterest.com\\/angelicasaario\\/\", \"isFamilyFriendly\": true, \"displayUrl\": \"https:\\/\\/www.pinterest.com\\/angelicasaario\", \"snippet\": \"Angelica Saario | Hey everyone! My ... Venus is the hottest planet in our solar system because its atmosphere has clouds made up of ... They form when high layers of ...\", \"dateLastCrawled\": \"2018-04-05T09:48:00.0000000Z\", \"language\": \"en\"}]}, \"rankingResponse\": {\"mainline\": {\"items\": [{\"answerType\": \"WebPages\", \"resultIndex\": 0, \"value\": {\"id\": \"https:\\/\\/api.cognitive.microsoft.com\\/api\\/v7\\/#WebPages.0\"}}, {\"answerType\": \"WebPages\", \"resultIndex\": 1, \"value\": {\"id\": \"https:\\/\\/api.cognitive.microsoft.com\\/api\\/v7\\/#WebPages.1\"}}, {\"answerType\": \"WebPages\", \"resultIndex\": 2, \"value\": {\"id\": \"https:\\/\\/api.cognitive.microsoft.com\\/api\\/v7\\/#WebPages.2\"}}, {\"answerType\": \"WebPages\", \"resultIndex\": 3, \"value\": {\"id\": \"https:\\/\\/api.cognitive.microsoft.com\\/api\\/v7\\/#WebPages.3\"}}, {\"answerType\": \"WebPages\", \"resultIndex\": 4, \"value\": {\"id\": \"https:\\/\\/api.cognitive.microsoft.com\\/api\\/v7\\/#WebPages.4\"}}, {\"answerType\": \"WebPages\", \"resultIndex\": 5, \"value\": {\"id\": \"https:\\/\\/api.cognitive.microsoft.com\\/api\\/v7\\/#WebPages.5\"}}, {\"answerType\": \"WebPages\", \"resultIndex\": 6, \"value\": {\"id\": \"https:\\/\\/api.cognitive.microsoft.com\\/api\\/v7\\/#WebPages.6\"}}, {\"answerType\": \"WebPages\", \"resultIndex\": 7, \"value\": {\"id\": \"https:\\/\\/api.cognitive.microsoft.com\\/api\\/v7\\/#WebPages.7\"}}, {\"answerType\": \"WebPages\", \"resultIndex\": 8, \"value\": {\"id\": \"https:\\/\\/api.cognitive.microsoft.com\\/api\\/v7\\/#WebPages.8\"}}, {\"answerType\": \"WebPages\", \"resultIndex\": 9, \"value\": {\"id\": \"https:\\/\\/api.cognitive.microsoft.com\\/api\\/v7\\/#WebPages.9\"}}]}}}",
        "relevantHeaders": {
          "BingAPIs-TraceId": "907ABCC15CC84EA994214910411CCC82",
          "BingAPIs-SessionId": "D557EC629FF4478B9618EF31AF72DF32",
          "X-MSEdge-ClientID": "2C72153F48E668672B7B1EF3494969E0",
          "BingAPIs-Market": "en-US",
          "X-MSEdge-Ref": "Ref A: 907ABCC15CC84EA994214910411CCC82 Ref B: BLUEDGE0216 Ref C: 2018-04-09T16:54:46Z"
        },
        "TotalResults": 239000
      },
      "SearchResultWithQuestionPrependedAndCaseInQuotes": {
        "jsonResult": "{\"_type\": \"SearchResponse\", \"queryContext\": {\"originalQuery\": \"the only rock song to exit our solar system in hard-copy form is by what artist? \\\"Chuck Berry\\\"\"}, \"webPages\": {\"webSearchUrl\": \"https:\\/\\/www.bing.com\\/search?q=the+only+rock+song+to+exit+our+solar+system+in+hard-copy+form+is+by+what+artist%3f+%22Chuck+Berry%22\", \"totalEstimatedMatches\": 26400, \"value\": [{\"id\": \"https:\\/\\/api.cognitive.microsoft.com\\/api\\/v7\\/#WebPages.0\", \"name\": \"Rock and Roll Music - WikiVisually\", \"url\": \"https:\\/\\/wikivisually.com\\/wiki\\/Rock_and_Roll_Music\", \"isFamilyFriendly\": true, \"displayUrl\": \"https:\\/\\/wikivisually.com\\/wiki\\/Rock_and_Roll_Music\", \"snippet\": \"\\\"Honkin' Down the Highway\\\" \\/ \\\"Solar System\\\" ... The only artist to have two songs dropped from ... and first recorded by Chuck Berry. The song was a hit among ...\", \"dateLastCrawled\": \"2018-02-20T02:13:00.0000000Z\", \"language\": \"en\"}, {\"id\": \"https:\\/\\/api.cognitive.microsoft.com\\/api\\/v7\\/#WebPages.1\", \"name\": \"What Is on Voyager’s Golden Record? | Science | Smithsonian\", \"url\": \"https:\\/\\/www.smithsonianmag.com\\/science-nature\\/what-is-on-voyagers-golden-record-73063839\\/\", \"isFamilyFriendly\": true, \"displayUrl\": \"https:\\/\\/www.smithsonianmag.com\\/science-nature\\/what-is-on-voyagers...\", \"snippet\": \"Produce a phonograph record containing the sounds and images of humankind and fling it out into the solar system. ... Chuck Berry’s ... arguing that rock music was ...\", \"dateLastCrawled\": \"2018-04-04T20:58:00.0000000Z\", \"language\": \"en\"}, {\"id\": \"https:\\/\\/api.cognitive.microsoft.com\\/api\\/v7\\/#WebPages.2\", \"name\": \"Bing Videos - Official Site\", \"url\": \"http:\\/\\/www.bing.com\\/videos\", \"about\": [{\"name\": \"Bing Videos\"}, {\"name\": \"Bing Videos\"}], \"isFamilyFriendly\": true, \"displayUrl\": \"www.bing.com\\/videos\", \"snippet\": \"Bing helps you turn information into action, making it faster and easier to go from searching to doing.\", \"dateLastCrawled\": \"2018-04-04T15:51:00.0000000Z\", \"language\": \"en\"}, {\"id\": \"https:\\/\\/api.cognitive.microsoft.com\\/api\\/v7\\/#WebPages.3\", \"name\": \"Astronomy - telescope.com\", \"url\": \"https:\\/\\/www.telescope.com\\/catalog\\/thumbnail.jsp?currentIndex=0&pageSize=225&defaultPageSize=20&mode=viewall&index=24&subCategoryId=199\", \"isFamilyFriendly\": true, \"displayUrl\": \"https:\\/\\/www.telescope.com\\/catalog\\/thumbnail.jsp?currentIndex=0&...\", \"snippet\": \"... to the innermost world in our Solar System. ... the edge of the Solar System. Artist's concept of ... song, Azerbaijani folk music and Chuck Berry; ...\", \"dateLastCrawled\": \"2018-03-18T04:43:00.0000000Z\", \"language\": \"en\"}, {\"id\": \"https:\\/\\/api.cognitive.microsoft.com\\/api\\/v7\\/#WebPages.4\", \"name\": \"24.0 - Interstellar Communication Techniques\", \"url\": \"http:\\/\\/www.bibliotecapleyades.net\\/vida_alien\\/xenology\\/24.0.htm\", \"about\": [{\"name\": \"Interstellar communication\"}], \"isFamilyFriendly\": true, \"displayUrl\": \"www.bibliotecapleyades.net\\/vida_alien\\/xenology\\/24.0.htm\", \"snippet\": \"Little was known of the actual conditions on the surface of Mars or any other planet in our solar system; ... the only (naturally occurring) form ... Chuck Berry . 8 ...\", \"dateLastCrawled\": \"2018-04-05T12:45:00.0000000Z\", \"language\": \"en\"}, {\"id\": \"https:\\/\\/api.cognitive.microsoft.com\\/api\\/v7\\/#WebPages.5\", \"name\": \"After Midnight : BBC Radio 2 - Internet Archive\", \"url\": \"https:\\/\\/archive.org\\/details\\/BBC_Radio_2_20160811_230000_After_Midnight\", \"isFamilyFriendly\": true, \"displayUrl\": \"https:\\/\\/archive.org\\/details\\/BBC_Radio_2_20160811_230000_After_Midnight\", \"snippet\": \"NASA Images Solar System Collection Ames ... go all the details of all the songs you'll find on our page ... air guitar like Chuck Berry featured artist searching ...\", \"dateLastCrawled\": \"2018-04-03T03:05:00.0000000Z\", \"language\": \"en\"}, {\"id\": \"https:\\/\\/api.cognitive.microsoft.com\\/api\\/v7\\/#WebPages.6\", \"name\": \"Dictionary.com's List of Every Word of the Year ...\", \"url\": \"http:\\/\\/www.dictionary.com\\/e\\/s\\/word-of-the-year-list\\/\", \"about\": [{\"name\": \"Word of the year\"}], \"isFamilyFriendly\": true, \"displayUrl\": \"www.dictionary.com\\/e\\/s\\/word-of-the-year-list\", \"snippet\": \"A list of every Word of the Year selection released by Dictionary.com. Dictionary.com's first Word of the Year ... Only time will tell if the ... Our choice for Word ...\", \"dateLastCrawled\": \"2018-04-05T15:43:00.0000000Z\", \"language\": \"en\"}, {\"id\": \"https:\\/\\/api.cognitive.microsoft.com\\/api\\/v7\\/#WebPages.7\", \"name\": \"The Beach Boys - RiNet\", \"url\": \"http:\\/\\/starling.rinet.ru\\/music\\/beachc.htm\", \"isFamilyFriendly\": true, \"displayUrl\": \"starling.rinet.ru\\/music\\/beachc.htm\", \"snippet\": \"Reviews of albums by the Beach Boys . ... songs about the solar system and Johnnie Carlson, ... which truly turned rock into an art form.\", \"dateLastCrawled\": \"2018-03-24T04:22:00.0000000Z\", \"language\": \"en\"}, {\"id\": \"https:\\/\\/api.cognitive.microsoft.com\\/api\\/v7\\/#WebPages.8\", \"name\": \"MSN News - Official Site\", \"url\": \"http:\\/\\/www.msn.com\\/en-us\\/news\", \"about\": [{\"name\": \"MSN\"}], \"isFamilyFriendly\": true, \"displayUrl\": \"www.msn.com\\/en-us\\/news\", \"snippet\": \"Stocks plunge as Trump's tweets rock Amazon ... press DC for gun control ahead of March for Our Lives CNN; ... Douglas will require students to carry only clear ...\", \"dateLastCrawled\": \"2018-04-04T07:10:00.0000000Z\", \"language\": \"en\"}, {\"id\": \"https:\\/\\/api.cognitive.microsoft.com\\/api\\/v7\\/#WebPages.9\", \"name\": \"Party Bands - live entertainment bands\", \"url\": \"http:\\/\\/www.gigs4all.com\\/party-bands.php\", \"isFamilyFriendly\": true, \"displayUrl\": \"www.gigs4all.com\\/party-bands.php\", \"snippet\": \"The bands shown on this page have specified Party Bands - live entertainment music as ... OUR MUSIC IS INFLUENCED BY SOUTHERN ROCK ... Sub Solar System ...\", \"dateLastCrawled\": \"2018-02-26T13:13:00.0000000Z\", \"language\": \"en\"}], \"someResultsRemoved\": true}, \"rankingResponse\": {\"mainline\": {\"items\": [{\"answerType\": \"WebPages\", \"resultIndex\": 0, \"value\": {\"id\": \"https:\\/\\/api.cognitive.microsoft.com\\/api\\/v7\\/#WebPages.0\"}}, {\"answerType\": \"WebPages\", \"resultIndex\": 1, \"value\": {\"id\": \"https:\\/\\/api.cognitive.microsoft.com\\/api\\/v7\\/#WebPages.1\"}}, {\"answerType\": \"WebPages\", \"resultIndex\": 2, \"value\": {\"id\": \"https:\\/\\/api.cognitive.microsoft.com\\/api\\/v7\\/#WebPages.2\"}}, {\"answerType\": \"WebPages\", \"resultIndex\": 3, \"value\": {\"id\": \"https:\\/\\/api.cognitive.microsoft.com\\/api\\/v7\\/#WebPages.3\"}}, {\"answerType\": \"WebPages\", \"resultIndex\": 4, \"value\": {\"id\": \"https:\\/\\/api.cognitive.microsoft.com\\/api\\/v7\\/#WebPages.4\"}}, {\"answerType\": \"WebPages\", \"resultIndex\": 5, \"value\": {\"id\": \"https:\\/\\/api.cognitive.microsoft.com\\/api\\/v7\\/#WebPages.5\"}}, {\"answerType\": \"WebPages\", \"resultIndex\": 6, \"value\": {\"id\": \"https:\\/\\/api.cognitive.microsoft.com\\/api\\/v7\\/#WebPages.6\"}}, {\"answerType\": \"WebPages\", \"resultIndex\": 7, \"value\": {\"id\": \"https:\\/\\/api.cognitive.microsoft.com\\/api\\/v7\\/#WebPages.7\"}}, {\"answerType\": \"WebPages\", \"resultIndex\": 8, \"value\": {\"id\": \"https:\\/\\/api.cognitive.microsoft.com\\/api\\/v7\\/#WebPages.8\"}}, {\"answerType\": \"WebPages\", \"resultIndex\": 9, \"value\": {\"id\": \"https:\\/\\/api.cognitive.microsoft.com\\/api\\/v7\\/#WebPages.9\"}}]}}}",
        "relevantHeaders": {
          "BingAPIs-TraceId": "1BD41B23B2174B309301F0B8F2CFD555",
          "BingAPIs-SessionId": "B5FD7E069712485FB527E87E48F70C54",
          "X-MSEdge-ClientID": "0EB1441FF50A6176047A4FD3F4A56023",
          "BingAPIs-Market": "en-US",
          "X-MSEdge-Ref": "Ref A: 1BD41B23B2174B309301F0B8F2CFD555 Ref B: BLUEDGE0117 Ref C: 2018-04-09T16:54:46Z"
        },
        "TotalResults": 26400
      },
      "TimesMentionedInQuestionSearchResult": 0,
      "Attributes": null,
      "IsCorrect": true
    },
    "3": {
      "Case": "Little Richard",
      "SearchResultWithQuestionPrepended": {
        "jsonResult": "{\"_type\": \"SearchResponse\", \"queryContext\": {\"originalQuery\": \"the only rock song to exit our solar system in hard-copy form is by what artist? Little Richard\"}, \"webPages\": {\"webSearchUrl\": \"https:\\/\\/www.bing.com\\/search?q=the+only+rock+song+to+exit+our+solar+system+in+hard-copy+form+is+by+what+artist%3f+Little+Richard\", \"totalEstimatedMatches\": 336000, \"value\": [{\"id\": \"https:\\/\\/api.cognitive.microsoft.com\\/api\\/v7\\/#WebPages.0\", \"name\": \"Did a SUPERNOVA trigger the birth of the solar system? - Daily Mail Online\", \"url\": \"http:\\/\\/www.dailymail.co.uk\\/sciencetech\\/article-3204590\\/Did-supernova-trigger-birth-solar-Shockwaves-triggered-formation-rotation-planets.html\", \"isFamilyFriendly\": true, \"displayUrl\": \"www.dailymail.co.uk\\/sciencetech\\/article-3204590\\/Did-supernova...\", \"snippet\": \"Scientists from the Carnegie Institution for Science in Washington have shown how a supernova explosion gave our solar system its spin, without which there would be no planets.\", \"dateLastCrawled\": \"2018-04-01T00:47:00.0000000Z\", \"language\": \"en\"}, {\"id\": \"https:\\/\\/api.cognitive.microsoft.com\\/api\\/v7\\/#WebPages.1\", \"name\": \"Myspace - Official Site\", \"url\": \"https:\\/\\/myspace.com\\/\", \"about\": [{\"name\": \"Myspace\"}, {\"name\": \"Myspace\"}], \"isFamilyFriendly\": true, \"displayUrl\": \"https:\\/\\/myspace.com\", \"snippet\": \"Movie buffs aren’t the only ones in for a treat at the ... It’s the story of a humble rock ... Welcome to Myspace. Just start typing to find music. Queue;\", \"deepLinks\": [{\"name\": \"Sign In\", \"url\": \"https:\\/\\/myspace.com\\/signin\"}, {\"name\": \"People\", \"url\": \"https:\\/\\/myspace.com\\/discover\\/people\"}, {\"name\": \"Search\", \"url\": \"https:\\/\\/myspace.com\\/search\"}, {\"name\": \"Music\", \"url\": \"https:\\/\\/myspace.com\\/discover\\/songs\"}, {\"name\": \"Help\", \"url\": \"https:\\/\\/help.myspace.com\\/hc\\/en-us\"}, {\"name\": \"MySpace Profile\", \"url\": \"https:\\/\\/myspace.com\\/myspace\"}], \"dateLastCrawled\": \"2018-04-05T11:32:00.0000000Z\", \"language\": \"en\"}, {\"id\": \"https:\\/\\/api.cognitive.microsoft.com\\/api\\/v7\\/#WebPages.2\", \"name\": \"Internet Archive - Official Site\", \"url\": \"https:\\/\\/www.archive.org\\/\", \"about\": [{\"name\": \"Internet Archive\"}, {\"name\": \"East of Borneo\"}, {\"name\": \"Riders of the Purple Sage\"}, {\"name\": \"Internet Archive\"}], \"isFamilyFriendly\": true, \"displayUrl\": \"https:\\/\\/www.archive.org\", \"snippet\": \"Internet Archive is a non-profit digital library offering free universal access to books, movies & music, ... NASA Images Solar System Collection Ames Research Center.\", \"dateLastCrawled\": \"2018-04-04T05:10:00.0000000Z\", \"language\": \"en\"}, {\"id\": \"https:\\/\\/api.cognitive.microsoft.com\\/api\\/v7\\/#WebPages.3\", \"name\": \"CAS – Central Authentication Service\", \"url\": \"https:\\/\\/my.msstate.edu\\/\", \"about\": [{\"name\": \"Mississippi State University\"}], \"isFamilyFriendly\": true, \"displayUrl\": \"https:\\/\\/my.msstate.edu\", \"snippet\": \"Central Authentication Service. ... For security reasons, please log out and exit your web browser when you are done accessing services that require authentication!\", \"dateLastCrawled\": \"2018-04-03T00:44:00.0000000Z\", \"language\": \"en\"}, {\"id\": \"https:\\/\\/api.cognitive.microsoft.com\\/api\\/v7\\/#WebPages.4\", \"name\": \"Academic Bowl Flashcards | Quizlet\", \"url\": \"https:\\/\\/quizlet.com\\/9174854\\/academic-bowl-flash-cards\\/\", \"isFamilyFriendly\": true, \"displayUrl\": \"https:\\/\\/quizlet.com\\/9174854\\/academic-bowl-flash-cards\", \"snippet\": \"Start studying Academic Bowl ... The Dome of the Rock is the third ... scientists discovered a great cyclone on the North Pole of what planet in our solar system?\", \"dateLastCrawled\": \"2018-03-26T04:45:00.0000000Z\", \"language\": \"en\"}, {\"id\": \"https:\\/\\/api.cognitive.microsoft.com\\/api\\/v7\\/#WebPages.5\", \"name\": \"MSN Video Player - Official Site\", \"url\": \"https:\\/\\/www.msn.com\\/en-gb\\/video\", \"isFamilyFriendly\": true, \"displayUrl\": \"https:\\/\\/www.msn.com\\/en-gb\\/video\", \"snippet\": \"Couple create worldwide lip sync video to Aladdin song ... US artist creates human body part cakes ... Dwayne \\\"The Rock\\\" Johnson Opens Up About His Battle With ...\", \"dateLastCrawled\": \"2018-04-05T14:05:00.0000000Z\", \"language\": \"en\"}, {\"id\": \"https:\\/\\/api.cognitive.microsoft.com\\/api\\/v7\\/#WebPages.6\", \"name\": \"Life on Mars - Wikipedia\", \"url\": \"https:\\/\\/en.wikipedia.org\\/wiki\\/Life_on_Mars\", \"about\": [{\"name\": \"Life on Mars\"}], \"isFamilyFriendly\": true, \"displayUrl\": \"https:\\/\\/en.wikipedia.org\\/wiki\\/Life_on_Mars\", \"snippet\": \"Habitability in the Solar System; ... rock microenvironments ... meteorites contain potential evidence of past life on Mars, in the form of microscopic ...\", \"dateLastCrawled\": \"2018-04-03T07:34:00.0000000Z\", \"language\": \"en\"}, {\"id\": \"https:\\/\\/api.cognitive.microsoft.com\\/api\\/v7\\/#WebPages.7\", \"name\": \"2001: A Space Odyssey (1968) - Trivia - IMDb\", \"url\": \"http:\\/\\/www.imdb.com\\/title\\/tt0062622\\/trivia\", \"about\": [{\"name\": \"2001: A Space Odyssey\"}, {\"name\": \"2001: A Space Odyssey\"}], \"isFamilyFriendly\": true, \"displayUrl\": \"www.imdb.com\\/title\\/tt0062622\\/trivia\", \"snippet\": \"2001: A Space Odyssey (1968) ... The joke working title, \\\"How the Solar System was Won\\\", ... Intermission, and Exit music ...\", \"dateLastCrawled\": \"2018-03-23T08:20:00.0000000Z\", \"language\": \"en\"}, {\"id\": \"https:\\/\\/api.cognitive.microsoft.com\\/api\\/v7\\/#WebPages.8\", \"name\": \"Dictionary.com's List of Every Word of the Year - Everything After Z\", \"url\": \"http:\\/\\/www.dictionary.com\\/e\\/s\\/word-of-the-year-list\\/\", \"about\": [{\"name\": \"Word of the year\"}], \"isFamilyFriendly\": true, \"displayUrl\": \"www.dictionary.com\\/e\\/s\\/word-of-the-year-list\", \"snippet\": \"A list of every Word of the Year selection released by Dictionary.com. Dictionary.com's first Word of the Year ... Only time will tell if the ... Our choice for Word ...\", \"dateLastCrawled\": \"2018-04-05T15:43:00.0000000Z\", \"language\": \"en\"}, {\"id\": \"https:\\/\\/api.cognitive.microsoft.com\\/api\\/v7\\/#WebPages.9\", \"name\": \"Planets As Consciousness Unit Formations\", \"url\": \"http:\\/\\/www.bibliotecapleyades.net\\/ciencia\\/ciencia_consciousuniverse03.htm\", \"isFamilyFriendly\": true, \"displayUrl\": \"www.bibliotecapleyades.net\\/ciencia\\/ciencia_consciousuniverse03.htm\", \"snippet\": \"The most recent NASA photographs have only increased the resolution with which we can view this ... Returning to our own Solar System, ... ammonia and rock, ...\", \"dateLastCrawled\": \"2018-04-04T14:06:00.0000000Z\", \"language\": \"en\"}]}, \"rankingResponse\": {\"mainline\": {\"items\": [{\"answerType\": \"WebPages\", \"resultIndex\": 0, \"value\": {\"id\": \"https:\\/\\/api.cognitive.microsoft.com\\/api\\/v7\\/#WebPages.0\"}}, {\"answerType\": \"WebPages\", \"resultIndex\": 1, \"value\": {\"id\": \"https:\\/\\/api.cognitive.microsoft.com\\/api\\/v7\\/#WebPages.1\"}}, {\"answerType\": \"WebPages\", \"resultIndex\": 2, \"value\": {\"id\": \"https:\\/\\/api.cognitive.microsoft.com\\/api\\/v7\\/#WebPages.2\"}}, {\"answerType\": \"WebPages\", \"resultIndex\": 3, \"value\": {\"id\": \"https:\\/\\/api.cognitive.microsoft.com\\/api\\/v7\\/#WebPages.3\"}}, {\"answerType\": \"WebPages\", \"resultIndex\": 4, \"value\": {\"id\": \"https:\\/\\/api.cognitive.microsoft.com\\/api\\/v7\\/#WebPages.4\"}}, {\"answerType\": \"WebPages\", \"resultIndex\": 5, \"value\": {\"id\": \"https:\\/\\/api.cognitive.microsoft.com\\/api\\/v7\\/#WebPages.5\"}}, {\"answerType\": \"WebPages\", \"resultIndex\": 6, \"value\": {\"id\": \"https:\\/\\/api.cognitive.microsoft.com\\/api\\/v7\\/#WebPages.6\"}}, {\"answerType\": \"WebPages\", \"resultIndex\": 7, \"value\": {\"id\": \"https:\\/\\/api.cognitive.microsoft.com\\/api\\/v7\\/#WebPages.7\"}}, {\"answerType\": \"WebPages\", \"resultIndex\": 8, \"value\": {\"id\": \"https:\\/\\/api.cognitive.microsoft.com\\/api\\/v7\\/#WebPages.8\"}}, {\"answerType\": \"WebPages\", \"resultIndex\": 9, \"value\": {\"id\": \"https:\\/\\/api.cognitive.microsoft.com\\/api\\/v7\\/#WebPages.9\"}}]}}}",
        "relevantHeaders": {
          "BingAPIs-TraceId": "3190AC20D03144DAB2D6E76535ACF9C8",
          "BingAPIs-SessionId": "D17F10A7B3CE4337AE51FE1385A73D20",
          "X-MSEdge-ClientID": "305C20D70D1C673234432B1B0CB366C2",
          "BingAPIs-Market": "en-US",
          "X-MSEdge-Ref": "Ref A: 3190AC20D03144DAB2D6E76535ACF9C8 Ref B: BLUEDGE0410 Ref C: 2018-04-09T16:54:46Z"
        },
        "TotalResults": 336000
      },
      "SearchResultWithQuestionPrependedAndCaseInQuotes": {
        "jsonResult": "{\"_type\": \"SearchResponse\", \"queryContext\": {\"originalQuery\": \"the only rock song to exit our solar system in hard-copy form is by what artist? \\\"Little Richard\\\"\"}, \"webPages\": {\"webSearchUrl\": \"https:\\/\\/www.bing.com\\/search?q=the+only+rock+song+to+exit+our+solar+system+in+hard-copy+form+is+by+what+artist%3f+%22Little+Richard%22\", \"totalEstimatedMatches\": 24400, \"value\": [{\"id\": \"https:\\/\\/api.cognitive.microsoft.com\\/api\\/v7\\/#WebPages.0\", \"name\": \"Dictionary.com's List of Every Word of the Year ...\", \"url\": \"http:\\/\\/www.dictionary.com\\/e\\/s\\/word-of-the-year-list\\/\", \"about\": [{\"name\": \"Word of the year\"}], \"isFamilyFriendly\": true, \"displayUrl\": \"www.dictionary.com\\/e\\/s\\/word-of-the-year-list\", \"snippet\": \"A list of every Word of the Year selection released by Dictionary.com. Dictionary.com's first Word of the Year ... Only time will tell if the ... Our choice for Word ...\", \"dateLastCrawled\": \"2018-04-05T15:43:00.0000000Z\", \"language\": \"en\"}, {\"id\": \"https:\\/\\/api.cognitive.microsoft.com\\/api\\/v7\\/#WebPages.1\", \"name\": \"The Beach Boys - RiNet\", \"url\": \"http:\\/\\/starling.rinet.ru\\/music\\/beachc.htm\", \"isFamilyFriendly\": true, \"displayUrl\": \"starling.rinet.ru\\/music\\/beachc.htm\", \"snippet\": \"Reviews of albums by the Beach Boys . ... songs about the solar system and Johnnie Carlson, ... which truly turned rock into an art form.\", \"dateLastCrawled\": \"2018-03-24T04:22:00.0000000Z\", \"language\": \"en\"}, {\"id\": \"https:\\/\\/api.cognitive.microsoft.com\\/api\\/v7\\/#WebPages.2\", \"name\": \"MSN News - Official Site\", \"url\": \"http:\\/\\/www.msn.com\\/en-us\\/news\", \"about\": [{\"name\": \"MSN\"}], \"isFamilyFriendly\": true, \"displayUrl\": \"www.msn.com\\/en-us\\/news\", \"snippet\": \"Stocks plunge as Trump's tweets rock Amazon ... press DC for gun control ahead of March for Our Lives CNN; ... Douglas will require students to carry only clear ...\", \"dateLastCrawled\": \"2018-04-04T07:10:00.0000000Z\", \"language\": \"en\"}, {\"id\": \"https:\\/\\/api.cognitive.microsoft.com\\/api\\/v7\\/#WebPages.3\", \"name\": \"To Inhabit the Solar System - Using the Water in Space ...\", \"url\": \"https:\\/\\/www.scribd.com\\/document\\/31815709\\/To-Inhabit-the-Solar-System-Using-the-Water-in-Space\", \"isFamilyFriendly\": true, \"displayUrl\": \"https:\\/\\/www.scribd.com\\/document\\/31815709\\/To-Inhabit-the-Solar...\", \"snippet\": \"To Inhabit the Solar System ... hundreds of us throughout the solar system, the only product of my entire career ... powerful than anything our Life Form had ...\", \"dateLastCrawled\": \"2018-03-24T22:25:00.0000000Z\", \"language\": \"en\"}, {\"id\": \"https:\\/\\/api.cognitive.microsoft.com\\/api\\/v7\\/#WebPages.4\", \"name\": \"Community Video : Free Movies : Download & Streaming ...\", \"url\": \"https:\\/\\/archive.org\\/details\\/opensource_movies?and%5B%5D=subject%3A%22Music%22&sort=&page=10\", \"isFamilyFriendly\": true, \"displayUrl\": \"https:\\/\\/archive.org\\/details\\/opensource_movies?and[]=subject:\\\"Music...\", \"snippet\": \"Animation & Cartoons Arts & Music Community Video Computers & Technology ... available on iTunes or hard copy at ... The sun in our solar system makes light so ...\", \"dateLastCrawled\": \"2018-03-17T06:39:00.0000000Z\", \"language\": \"en\"}, {\"id\": \"https:\\/\\/api.cognitive.microsoft.com\\/api\\/v7\\/#WebPages.5\", \"name\": \"The Big Dish (band) - topics.revolvy.com\", \"url\": \"https:\\/\\/topics.revolvy.com\\/topic\\/The%20Big%20Dish%20(band)&item_type=topic\", \"about\": [{\"name\": \"The Big Dish\"}], \"isFamilyFriendly\": true, \"displayUrl\": \"https:\\/\\/topics.revolvy.com\\/topic\\/The Big Dish (band)&item_type=topic\", \"snippet\": \"Lindsay returned to the fold in late 2004 on his own Seminal label with the piano-driven Exit Music ... The Big Dish may refer to; The Big Dish (band ... solar system ...\", \"dateLastCrawled\": \"2017-07-29T01:23:00.0000000Z\", \"language\": \"en\"}, {\"id\": \"https:\\/\\/api.cognitive.microsoft.com\\/api\\/v7\\/#WebPages.6\", \"name\": \"Eight Miles Higher: May 2016 - Andrew Darlington\", \"url\": \"http:\\/\\/andrewdarlington.blogspot.com\\/2016\\/05\\/\", \"isFamilyFriendly\": true, \"displayUrl\": \"andrewdarlington.blogspot.com\\/2016\\/05\", \"snippet\": \"in truth, the campaign gets dirty, very quickly, Andrew Marr suggests Muddy Puddle Jumping is not the answer to economic instability, that species-integration in the classroom will\", \"dateLastCrawled\": \"2018-03-24T16:12:00.0000000Z\", \"language\": \"en\"}, {\"id\": \"https:\\/\\/api.cognitive.microsoft.com\\/api\\/v7\\/#WebPages.7\", \"name\": \"Archives - Philly.com\", \"url\": \"http:\\/\\/www.philly.com\\/philly\\/archives\\/\", \"about\": [{\"name\": \"Adult Diagnostic And Treatment Center\"}, {\"name\": \"Cardinal Dougherty High School\"}, {\"name\": \"Adult Diagnostic And Treatment Center\"}, {\"name\": \"Cardinal Dougherty High School\"}], \"isFamilyFriendly\": true, \"displayUrl\": \"www.philly.com\\/philly\\/archives\", \"snippet\": \"Archives and past articles from the Philadelphia Inquirer, ... Search and browse our historical collection to find news, ... please fill out the Request a Photo form.\", \"dateLastCrawled\": \"2018-04-02T23:17:00.0000000Z\", \"language\": \"en\"}, {\"id\": \"https:\\/\\/api.cognitive.microsoft.com\\/api\\/v7\\/#WebPages.8\", \"name\": \"Party Bands - live entertainment bands\", \"url\": \"http:\\/\\/www.gigs4all.com\\/party-bands.php\", \"isFamilyFriendly\": true, \"displayUrl\": \"www.gigs4all.com\\/party-bands.php\", \"snippet\": \"The bands shown on this page have specified Party Bands - live entertainment music as ... OUR MUSIC IS INFLUENCED BY SOUTHERN ROCK ... Sub Solar System ...\", \"dateLastCrawled\": \"2018-02-26T13:13:00.0000000Z\", \"language\": \"en\"}, {\"id\": \"https:\\/\\/api.cognitive.microsoft.com\\/api\\/v7\\/#WebPages.9\", \"name\": \"\\/Sports&Leisure\\/Charles Barkley\\/Barkley\\/\\/Who played hoops ...\", \"url\": \"https:\\/\\/pastebin.com\\/fmZttGNk\", \"isFamilyFriendly\": true, \"displayUrl\": \"https:\\/\\/pastebin.com\\/fmZttGNk\", \"snippet\": \"\\/Science&Nature\\/Tutti Frutti\\/\\/Which of Little Richard's songs did a Georgia politician push as the state rock song? ... 9 planets in our solar system is blue and ...\", \"dateLastCrawled\": \"2018-03-18T08:18:00.0000000Z\", \"language\": \"en\"}]}, \"rankingResponse\": {\"mainline\": {\"items\": [{\"answerType\": \"WebPages\", \"resultIndex\": 0, \"value\": {\"id\": \"https:\\/\\/api.cognitive.microsoft.com\\/api\\/v7\\/#WebPages.0\"}}, {\"answerType\": \"WebPages\", \"resultIndex\": 1, \"value\": {\"id\": \"https:\\/\\/api.cognitive.microsoft.com\\/api\\/v7\\/#WebPages.1\"}}, {\"answerType\": \"WebPages\", \"resultIndex\": 2, \"value\": {\"id\": \"https:\\/\\/api.cognitive.microsoft.com\\/api\\/v7\\/#WebPages.2\"}}, {\"answerType\": \"WebPages\", \"resultIndex\": 3, \"value\": {\"id\": \"https:\\/\\/api.cognitive.microsoft.com\\/api\\/v7\\/#WebPages.3\"}}, {\"answerType\": \"WebPages\", \"resultIndex\": 4, \"value\": {\"id\": \"https:\\/\\/api.cognitive.microsoft.com\\/api\\/v7\\/#WebPages.4\"}}, {\"answerType\": \"WebPages\", \"resultIndex\": 5, \"value\": {\"id\": \"https:\\/\\/api.cognitive.microsoft.com\\/api\\/v7\\/#WebPages.5\"}}, {\"answerType\": \"WebPages\", \"resultIndex\": 6, \"value\": {\"id\": \"https:\\/\\/api.cognitive.microsoft.com\\/api\\/v7\\/#WebPages.6\"}}, {\"answerType\": \"WebPages\", \"resultIndex\": 7, \"value\": {\"id\": \"https:\\/\\/api.cognitive.microsoft.com\\/api\\/v7\\/#WebPages.7\"}}, {\"answerType\": \"WebPages\", \"resultIndex\": 8, \"value\": {\"id\": \"https:\\/\\/api.cognitive.microsoft.com\\/api\\/v7\\/#WebPages.8\"}}, {\"answerType\": \"WebPages\", \"resultIndex\": 9, \"value\": {\"id\": \"https:\\/\\/api.cognitive.microsoft.com\\/api\\/v7\\/#WebPages.9\"}}]}}}",
        "relevantHeaders": {
          "BingAPIs-TraceId": "652127D055FB42439935743A9676012D",
          "BingAPIs-SessionId": "1A3DE3657637419E8A9F141B34102105",
          "X-MSEdge-ClientID": "3E6678DEEC19680C22607312EDB66911",
          "BingAPIs-Market": "en-US",
          "X-MSEdge-Ref": "Ref A: 652127D055FB42439935743A9676012D Ref B: BLUEDGE0323 Ref C: 2018-04-09T16:54:46Z"
        },
        "TotalResults": 24400
      },
      "TimesMentionedInQuestionSearchResult": 0,
      "Attributes": null,
      "IsCorrect": false
    }
  }
}